Workbook

Sheet 说明
A2: 视频模型成本与售价利润表
A6: · 生成时间：2026-09-29 · 数据口径：单条视频、输出 1 个；音频（有声/静音）在所有渠道成本相同，不单独区分。
A8: · 覆盖渠道：Ark 官方（Seedance 2.5 / 2.0 / 2.0 Mini）、MiniMax 官方（H3 / H3-Max）、GASIC 中转（Seedance 按条）、阿里百炼（Wan3.0 北京 + 国际）。
A10: · 成本公式：Seedance 系 = ROUNDUP(时长×宽×高×24/1024) tokens ÷ 1e6 × 元/百万tokens；MiniMax = 输出秒 × 元/秒；GASIC = 2 元/条；百炼 Wan3.0 =（输出秒 + 输入视频秒）× 元/秒。
A12: · Wan3.0 编辑/延长/参考模式的输入视频按秒计费，表中“输入视频秒”列按典型值 5 秒估算（可在明细表 F 列按实际输入时长修改）。
A14: · 现行售价 = 平台现行报价（预扣最高成本候选，向上取整到 1 积分）→ 当前基本零加价，仅作对照。
A16: · 建议售价 = 成本 ÷ (1 − 毛利率)，毛利率按单条成本对数插值：最便宜行 80% → 最货行 40%，夹在 30%~95%；低参数行落在 50%~100%，高参数行落在 30%~50%。
A18: · 想调价：改『费率与参数』里的黄色费率/参数，或直接改『建议售价清单』H 列（目标毛利率）——全表与曲线自动重算（请用 Excel / WPS 打开）。
A20: · 费率来源：Seedance 2.5/2.0 = 官方文档价（已实测校准）；Mini = 2.0 牌价×官方 4 折活动（暂定）；MiniMax = 官方秒单价；GASIC = 2 元/条；百炼 Wan3.0 = 官方牌价（北京限时 7 折实付更低，已备注）。
A22: · 官方价格页：ark.volcengine.com/region:cn-beijing/docs/ark/model-pricing（Seedance）、docs.bailian.console.aliyun.com/zh/model-studio/model-pricing（万相3.0）。

Sheet 费率与参数
A1: ① 通用参数（黄色单元格可改，全表自动重算）
A2: 积分单价（元/积分） | B2: 0.01 | C2: 平台现状：1积分 = 0.01元
A3: 积分取整步长（积分） | B3: 1 | C3: 报价向上取整到该步长
A4: 最低积分 | B4: 1 | C4: 单任务最低预扣/售价
A5: 毛利率上限（低参数端） | B5: 0.5 | C5: 落在 50%~100% 区间
A6: 毛利率下限（高参数端） | B6: 0.15 | C6: 落在 30%~50% 区间
A8: ② Seedance 像素预设（token 计费公式用：tokens = ROUNDUP(时长×宽×高×帧率/1024)）
A9: 分辨率 | B9: 宽 | C9: 高 | D9: 帧率
A10: 480p | B10: 854 | C10: 480 | D10: 24
A11: 720p | B11: 1280 | C11: 720 | D11: 24
A12: 1080p | B12: 1920 | C12: 1080 | D12: 24
A14: ③ 成本费率表（黄色费率可改；改后两张明细表与曲线自动重算）
A15: 费率键（路由|渠道|分辨率） | B15: 路由 | C15: 渠道 | D15: 分辨率 | E15: 计费模式 | F15: 费率 | G15: 单位 | H15: 备注
A16: seedance-2.5|Ark官方|480p | B16: Seedance 2.5 | C16: Ark官方 | D16: 480p | E16: token | F16: 60 | G16: 元/百万tokens | H16: 官方文档价
A17: seedance-2.5|Ark官方|720p | B17: Seedance 2.5 | C17: Ark官方 | D17: 720p | E17: token | F17: 90 | G17: 元/百万tokens | H17: 官方文档价
A18: seedance-2.5|Ark官方|1080p | B18: Seedance 2.5 | C18: Ark官方 | D18: 1080p | E18: token | F18: 150 | G18: 元/百万tokens | H18: 官方文档价
A19: seedance-2.0|Ark官方|480p | B19: Seedance 2.0 | C19: Ark官方 | D19: 480p | E19: token | F19: 30 | G19: 元/百万tokens | H19: 官方文档价
A20: seedance-2.0|Ark官方|720p | B20: Seedance 2.0 | C20: Ark官方 | D20: 720p | E20: token | F20: 45 | G20: 元/百万tokens | H20: 官方文档价
A21: seedance-2.0|Ark官方|1080p | B21: Seedance 2.0 | C21: Ark官方 | D21: 1080p | E21: token | F21: 75 | G21: 元/百万tokens | H21: 官方文档价
A22: seedance-2.0-mini|Ark官方|480p | B22: Seedance 2.0 Mini（极速版） | C22: Ark官方 | D22: 480p | E22: token | F22: 12 | G22: 元/百万tokens | H22: 暂定：2.0牌价×官方4折活动，待核对
A23: seedance-2.0-mini|Ark官方|720p | B23: Seedance 2.0 Mini（极速版） | C23: Ark官方 | D23: 720p | E23: token | F23: 18 | G23: 元/百万tokens | H23: 暂定：同上
A24: seedance-2.0-mini|Ark官方|1080p | B24: Seedance 2.0 Mini（极速版） | C24: Ark官方 | D24: 1080p | E24: token | F24: 30 | G24: 元/百万tokens | H24: 暂定：同上
A25: minimax-h3|MiniMax官方|768p | B25: MiniMax H3（海螺） | C25: MiniMax官方 | D25: 768p | E25: per_second | F25: 0.5 | G25: 元/秒 | H25: 官方 0.50元/秒
A26: minimax-h3|MiniMax官方|2k | B26: MiniMax H3（海螺） | C26: MiniMax官方 | D26: 2k | E26: per_second | F26: 0.8 | G26: 元/秒 | H26: 官方 0.80元/秒
A27: minimax-h3-max|MiniMax官方|480p | B27: MiniMax H3-Max（海螺） | C27: MiniMax官方 | D27: 480p | E27: per_second | F27: 0.5 | G27: 元/秒 | H27: 官方未公布，暂按 0.50元/秒
... A36: wan3.0-video|百炼（国际）|1080p | B36: 万相3.0（Wan3.0） | C36: 百炼（国际） | D36: 1080p | E36: per_second | F36: 1.49884 | G36: 元/秒 | H36: 国际站牌价
A38: 计费模式：token = 按生成 tokens（Seedance 系）；per_second = 按秒（MiniMax、百炼 Wan3.0）；per_task = 按条（GASIC）。
A39: 百炼 Wan3.0 计费时长 = 输入视频时长 + 输出视频时长（编辑/延长/参考模式），失败不计费；北京地域 30 秒免费额度未计入。音频（有声/静音）各渠道成本相同，不单独区分。

Sheet 成本与现售价
A1: 成本与现行售价明细（现行售价 = 预扣最高成本候选 → 平台当前基本零加价，用于对照）
A3: 路由 | B3: 渠道 | C3: 模型 | D3: 分辨率 | E3: 时长(秒) | F3: 输入视频秒 | G3: 计费模式 | H3: tokens | I3: 成本(元) | J3: 现售价(积分) | K3: 现售价(元) | L3: 现行毛利率
A4: Seedance 2.5 | B4: Ark官方 | C4: doubao-seedance-2-5-260628 | D4: 480p | E4: 5 | F4: — | G4: token | H4: =ROUNDUP(E4*VLOOKUP(D4,费率与参数!$A$10:$D$12,2,0)*VLOOKUP(D4,费率与参数!$A$10:$D$12,3,0)*VLOOKUP(D4,费率与参数!$A$10:$D$12,4,0)/1024,0) -> 48038 | I4: =H4*VLOOKUP("seedance-2.5|Ark官方|480p",费率与参数!$A$16:$G$36,6,0)/1000000 -> 2.88228 | J4: =MAX(费率与参数!$B$4,CEILING(I4/费率与参数!$B$2,费率与参数!$B$3)) -> 289 | K4: =J4*费率与参数!$B$2 -> 2.89 | L4: =IF(K4>0,1-I4/K4,0) -> 0.0026712803
A5: Seedance 2.5 | B5: Ark官方 | C5: doubao-seedance-2-5-260628 | D5: 480p | E5: 10 | F5: — | G5: token | H5: =ROUNDUP(E5*VLOOKUP(D5,费率与参数!$A$10:$D$12,2,0)*VLOOKUP(D5,费率与参数!$A$10:$D$12,3,0)*VLOOKUP(D5,费率与参数!$A$10:$D$12,4,0)/1024,0) -> 96075 | I5: =H5*VLOOKUP("seedance-2.5|Ark官方|480p",费率与参数!$A$16:$G$36,6,0)/1000000 -> 5.7645 | J5: =MAX(费率与参数!$B$4,CEILING(I5/费率与参数!$B$2,费率与参数!$B$3)) -> 577 | K5: =J5*费率与参数!$B$2 -> 5.77 | L5: =IF(K5>0,1-I5/K5,0) -> 0.00095320624
A6: Seedance 2.5 | B6: Ark官方 | C6: doubao-seedance-2-5-260628 | D6: 720p | E6: 5 | F6: — | G6: token | H6: =ROUNDUP(E6*VLOOKUP(D6,费率与参数!$A$10:$D$12,2,0)*VLOOKUP(D6,费率与参数!$A$10:$D$12,3,0)*VLOOKUP(D6,费率与参数!$A$10:$D$12,4,0)/1024,0) -> 108000 | I6: =H6*VLOOKUP("seedance-2.5|Ark官方|720p",费率与参数!$A$16:$G$36,6,0)/1000000 -> 9.72 | J6: =MAX(费率与参数!$B$4,CEILING(I6/费率与参数!$B$2,费率与参数!$B$3)) -> 972 | K6: =J6*费率与参数!$B$2 -> 9.72 | L6: =IF(K6>0,1-I6/K6,0) -> 0
A7: Seedance 2.5 | B7: Ark官方 | C7: doubao-seedance-2-5-260628 | D7: 720p | E7: 10 | F7: — | G7: token | H7: =ROUNDUP(E7*VLOOKUP(D7,费率与参数!$A$10:$D$12,2,0)*VLOOKUP(D7,费率与参数!$A$10:$D$12,3,0)*VLOOKUP(D7,费率与参数!$A$10:$D$12,4,0)/1024,0) -> 216000 | I7: =H7*VLOOKUP("seedance-2.5|Ark官方|720p",费率与参数!$A$16:$G$36,6,0)/1000000 -> 19.44 | J7: =MAX(费率与参数!$B$4,CEILING(I7/费率与参数!$B$2,费率与参数!$B$3)) -> 1944 | K7: =J7*费率与参数!$B$2 -> 19.44 | L7: =IF(K7>0,1-I7/K7,0) -> 0
A8: Seedance 2.5 | B8: Ark官方 | C8: doubao-seedance-2-5-260628 | D8: 1080p | E8: 5 | F8: — | G8: token | H8: =ROUNDUP(E8*VLOOKUP(D8,费率与参数!$A$10:$D$12,2,0)*VLOOKUP(D8,费率与参数!$A$10:$D$12,3,0)*VLOOKUP(D8,费率与参数!$A$10:$D$12,4,0)/1024,0) -> 243000 | I8: =H8*VLOOKUP("seedance-2.5|Ark官方|1080p",费率与参数!$A$16:$G$36,6,0)/1000000 -> 36.45 | J8: =MAX(费率与参数!$B$4,CEILING(I8/费率与参数!$B$2,费率与参数!$B$3)) -> 3645 | K8: =J8*费率与参数!$B$2 -> 36.45 | L8: =IF(K8>0,1-I8/K8,0) -> 0
A9: Seedance 2.5 | B9: Ark官方 | C9: doubao-seedance-2-5-260628 | D9: 1080p | E9: 10 | F9: — | G9: token | H9: =ROUNDUP(E9*VLOOKUP(D9,费率与参数!$A$10:$D$12,2,0)*VLOOKUP(D9,费率与参数!$A$10:$D$12,3,0)*VLOOKUP(D9,费率与参数!$A$10:$D$12,4,0)/1024,0) -> 486000 | I9: =H9*VLOOKUP("seedance-2.5|Ark官方|1080p",费率与参数!$A$16:$G$36,6,0)/1000000 -> 72.9 | J9: =MAX(费率与参数!$B$4,CEILING(I9/费率与参数!$B$2,费率与参数!$B$3)) -> 7290 | K9: =J9*费率与参数!$B$2 -> 72.9 | L9: =IF(K9>0,1-I9/K9,0) -> 0
A10: Seedance 2.5 | B10: GASIC中转 | C10: doubao-seedance-2-5-260628 | D10: 480p | E10: 任意 | F10: — | G10: 按条 | H10: — | I10: =VLOOKUP("seedance-2.5|GASIC中转|任意",费率与参数!$A$16:$G$36,6,0) -> 2 | J10: =MAX(费率与参数!$B$4,CEILING(I10/费率与参数!$B$2,费率与参数!$B$3)) -> 200 | K10: =J10*费率与参数!$B$2 -> 2 | L10: =IF(K10>0,1-I10/K10,0) -> 0
A11: Seedance 2.5 | B11: GASIC中转 | C11: doubao-seedance-2-5-260628 | D11: 480p | E11: 任意 | F11: — | G11: 按条 | H11: — | I11: =VLOOKUP("seedance-2.5|GASIC中转|任意",费率与参数!$A$16:$G$36,6,0) -> 2 | J11: =MAX(费率与参数!$B$4,CEILING(I11/费率与参数!$B$2,费率与参数!$B$3)) -> 200 | K11: =J11*费率与参数!$B$2 -> 2 | L11: =IF(K11>0,1-I11/K11,0) -> 0
A12: Seedance 2.5 | B12: GASIC中转 | C12: doubao-seedance-2-5-260628 | D12: 480p | E12: 任意 | F12: — | G12: 按条 | H12: — | I12: =VLOOKUP("seedance-2.5|GASIC中转|任意",费率与参数!$A$16:$G$36,6,0) -> 2 | J12: =MAX(费率与参数!$B$4,CEILING(I12/费率与参数!$B$2,费率与参数!$B$3)) -> 200 | K12: =J12*费率与参数!$B$2 -> 2 | L12: =IF(K12>0,1-I12/K12,0) -> 0
A13: Seedance 2.5 | B13: GASIC中转 | C13: doubao-seedance-2-5-260628 | D13: 720p | E13: 任意 | F13: — | G13: 按条 | H13: — | I13: =VLOOKUP("seedance-2.5|GASIC中转|任意",费率与参数!$A$16:$G$36,6,0) -> 2 | J13: =MAX(费率与参数!$B$4,CEILING(I13/费率与参数!$B$2,费率与参数!$B$3)) -> 200 | K13: =J13*费率与参数!$B$2 -> 2 | L13: =IF(K13>0,1-I13/K13,0) -> 0
A14: Seedance 2.5 | B14: GASIC中转 | C14: doubao-seedance-2-5-260628 | D14: 720p | E14: 任意 | F14: — | G14: 按条 | H14: — | I14: =VLOOKUP("seedance-2.5|GASIC中转|任意",费率与参数!$A$16:$G$36,6,0) -> 2 | J14: =MAX(费率与参数!$B$4,CEILING(I14/费率与参数!$B$2,费率与参数!$B$3)) -> 200 | K14: =J14*费率与参数!$B$2 -> 2 | L14: =IF(K14>0,1-I14/K14,0) -> 0
A15: Seedance 2.5 | B15: GASIC中转 | C15: doubao-seedance-2-5-260628 | D15: 720p | E15: 任意 | F15: — | G15: 按条 | H15: — | I15: =VLOOKUP("seedance-2.5|GASIC中转|任意",费率与参数!$A$16:$G$36,6,0) -> 2 | J15: =MAX(费率与参数!$B$4,CEILING(I15/费率与参数!$B$2,费率与参数!$B$3)) -> 200 | K15: =J15*费率与参数!$B$2 -> 2 | L15: =IF(K15>0,1-I15/K15,0) -> 0
A16: Seedance 2.5 | B16: GASIC中转 | C16: doubao-seedance-2-5-260628 | D16: 1080p | E16: 任意 | F16: — | G16: 按条 | H16: — | I16: =VLOOKUP("seedance-2.5|GASIC中转|任意",费率与参数!$A$16:$G$36,6,0) -> 2 | J16: =MAX(费率与参数!$B$4,CEILING(I16/费率与参数!$B$2,费率与参数!$B$3)) -> 200 | K16: =J16*费率与参数!$B$2 -> 2 | L16: =IF(K16>0,1-I16/K16,0) -> 0
A17: Seedance 2.5 | B17: GASIC中转 | C17: doubao-seedance-2-5-260628 | D17: 1080p | E17: 任意 | F17: — | G17: 按条 | H17: — | I17: =VLOOKUP("seedance-2.5|GASIC中转|任意",费率与参数!$A$16:$G$36,6,0) -> 2 | J17: =MAX(费率与参数!$B$4,CEILING(I17/费率与参数!$B$2,费率与参数!$B$3)) -> 200 | K17: =J17*费率与参数!$B$2 -> 2 | L17: =IF(K17>0,1-I17/K17,0) -> 0
A18: Seedance 2.5 | B18: GASIC中转 | C18: doubao-seedance-2-5-260628 | D18: 1080p | E18: 任意 | F18: — | G18: 按条 | H18: — | I18: =VLOOKUP("seedance-2.5|GASIC中转|任意",费率与参数!$A$16:$G$36,6,0) -> 2 | J18: =MAX(费率与参数!$B$4,CEILING(I18/费率与参数!$B$2,费率与参数!$B$3)) -> 200 | K18: =J18*费率与参数!$B$2 -> 2 | L18: =IF(K18>0,1-I18/K18,0) -> 0
A19: Seedance 2.0 | B19: Ark官方 | C19: doubao-seedance-2-0-260128 | D19: 480p | E19: 5 | F19: — | G19: token | H19: =ROUNDUP(E19*VLOOKUP(D19,费率与参数!$A$10:$D$12,2,0)*VLOOKUP(D19,费率与参数!$A$10:$D$12,3,0)*VLOOKUP(D19,费率与参数!$A$10:$D$12,4,0)/1024,0) -> 48038 | I19: =H19*VLOOKUP("seedance-2.0|Ark官方|480p",费率与参数!$A$16:$G$36,6,0)/1000000 -> 1.44114 | J19: =MAX(费率与参数!$B$4,CEILING(I19/费率与参数!$B$2,费率与参数!$B$3)) -> 145 | K19: =J19*费率与参数!$B$2 -> 1.45 | L19: =IF(K19>0,1-I19/K19,0) -> 0.0061103448
A20: Seedance 2.0 | B20: Ark官方 | C20: doubao-seedance-2-0-260128 | D20: 480p | E20: 10 | F20: — | G20: token | H20: =ROUNDUP(E20*VLOOKUP(D20,费率与参数!$A$10:$D$12,2,0)*VLOOKUP(D20,费率与参数!$A$10:$D$12,3,0)*VLOOKUP(D20,费率与参数!$A$10:$D$12,4,0)/1024,0) -> 96075 | I20: =H20*VLOOKUP("seedance-2.0|Ark官方|480p",费率与参数!$A$16:$G$36,6,0)/1000000 -> 2.88225 | J20: =MAX(费率与参数!$B$4,CEILING(I20/费率与参数!$B$2,费率与参数!$B$3)) -> 289 | K20: =J20*费率与参数!$B$2 -> 2.89 | L20: =IF(K20>0,1-I20/K20,0) -> 0.0026816609
A21: Seedance 2.0 | B21: Ark官方 | C21: doubao-seedance-2-0-260128 | D21: 720p | E21: 5 | F21: — | G21: token | H21: =ROUNDUP(E21*VLOOKUP(D21,费率与参数!$A$10:$D$12,2,0)*VLOOKUP(D21,费率与参数!$A$10:$D$12,3,0)*VLOOKUP(D21,费率与参数!$A$10:$D$12,4,0)/1024,0) -> 108000 | I21: =H21*VLOOKUP("seedance-2.0|Ark官方|720p",费率与参数!$A$16:$G$36,6,0)/1000000 -> 4.86 | J21: =MAX(费率与参数!$B$4,CEILING(I21/费率与参数!$B$2,费率与参数!$B$3)) -> 486 | K21: =J21*费率与参数!$B$2 -> 4.86 | L21: =IF(K21>0,1-I21/K21,0) -> 0
A22: Seedance 2.0 | B22: Ark官方 | C22: doubao-seedance-2-0-260128 | D22: 720p | E22: 10 | F22: — | G22: token | H22: =ROUNDUP(E22*VLOOKUP(D22,费率与参数!$A$10:$D$12,2,0)*VLOOKUP(D22,费率与参数!$A$10:$D$12,3,0)*VLOOKUP(D22,费率与参数!$A$10:$D$12,4,0)/1024,0) -> 216000 | I22: =H22*VLOOKUP("seedance-2.0|Ark官方|720p",费率与参数!$A$16:$G$36,6,0)/1000000 -> 9.72 | J22: =MAX(费率与参数!$B$4,CEILING(I22/费率与参数!$B$2,费率与参数!$B$3)) -> 972 | K22: =J22*费率与参数!$B$2 -> 9.72 | L22: =IF(K22>0,1-I22/K22,0) -> 0
A23: Seedance 2.0 | B23: Ark官方 | C23: doubao-seedance-2-0-260128 | D23: 1080p | E23: 5 | F23: — | G23: token | H23: =ROUNDUP(E23*VLOOKUP(D23,费率与参数!$A$10:$D$12,2,0)*VLOOKUP(D23,费率与参数!$A$10:$D$12,3,0)*VLOOKUP(D23,费率与参数!$A$10:$D$12,4,0)/1024,0) -> 243000 | I23: =H23*VLOOKUP("seedance-2.0|Ark官方|1080p",费率与参数!$A$16:$G$36,6,0)/1000000 -> 18.225 | J23: =MAX(费率与参数!$B$4,CEILING(I23/费率与参数!$B$2,费率与参数!$B$3)) -> 1823 | K23: =J23*费率与参数!$B$2 -> 18.23 | L23: =IF(K23>0,1-I23/K23,0) -> 0.00027427318
A24: Seedance 2.0 | B24: Ark官方 | C24: doubao-seedance-2-0-260128 | D24: 1080p | E24: 10 | F24: — | G24: token | H24: =ROUNDUP(E24*VLOOKUP(D24,费率与参数!$A$10:$D$12,2,0)*VLOOKUP(D24,费率与参数!$A$10:$D$12,3,0)*VLOOKUP(D24,费率与参数!$A$10:$D$12,4,0)/1024,0) -> 486000 | I24: =H24*VLOOKUP("seedance-2.0|Ark官方|1080p",费率与参数!$A$16:$G$36,6,0)/1000000 -> 36.45 | J24: =MAX(费率与参数!$B$4,CEILING(I24/费率与参数!$B$2,费率与参数!$B$3)) -> 3645 | K24: =J24*费率与参数!$B$2 -> 36.45 | L24: =IF(K24>0,1-I24/K24,0) -> 0
A25: Seedance 2.0 | B25: GASIC中转 | C25: doubao-seedance-2-0-260128 | D25: 480p | E25: 任意 | F25: — | G25: 按条 | H25: — | I25: =VLOOKUP("seedance-2.0|GASIC中转|任意",费率与参数!$A$16:$G$36,6,0) -> 2 | J25: =MAX(费率与参数!$B$4,CEILING(I25/费率与参数!$B$2,费率与参数!$B$3)) -> 200 | K25: =J25*费率与参数!$B$2 -> 2 | L25: =IF(K25>0,1-I25/K25,0) -> 0
A26: Seedance 2.0 | B26: GASIC中转 | C26: doubao-seedance-2-0-260128 | D26: 480p | E26: 任意 | F26: — | G26: 按条 | H26: — | I26: =VLOOKUP("seedance-2.0|GASIC中转|任意",费率与参数!$A$16:$G$36,6,0) -> 2 | J26: =MAX(费率与参数!$B$4,CEILING(I26/费率与参数!$B$2,费率与参数!$B$3)) -> 200 | K26: =J26*费率与参数!$B$2 -> 2 | L26: =IF(K26>0,1-I26/K26,0) -> 0
A27: Seedance 2.0 | B27: GASIC中转 | C27: doubao-seedance-2-0-260128 | D27: 720p | E27: 任意 | F27: — | G27: 按条 | H27: — | I27: =VLOOKUP("seedance-2.0|GASIC中转|任意",费率与参数!$A$16:$G$36,6,0) -> 2 | J27: =MAX(费率与参数!$B$4,CEILING(I27/费率与参数!$B$2,费率与参数!$B$3)) -> 200 | K27: =J27*费率与参数!$B$2 -> 2 | L27: =IF(K27>0,1-I27/K27,0) -> 0
A28: Seedance 2.0 | B28: GASIC中转 | C28: doubao-seedance-2-0-260128 | D28: 720p | E28: 任意 | F28: — | G28: 按条 | H28: — | I28: =VLOOKUP("seedance-2.0|GASIC中转|任意",费率与参数!$A$16:$G$36,6,0) -> 2 | J28: =MAX(费率与参数!$B$4,CEILING(I28/费率与参数!$B$2,费率与参数!$B$3)) -> 200 | K28: =J28*费率与参数!$B$2 -> 2 | L28: =IF(K28>0,1-I28/K28,0) -> 0
A29: Seedance 2.0 | B29: GASIC中转 | C29: doubao-seedance-2-0-260128 | D29: 1080p | E29: 任意 | F29: — | G29: 按条 | H29: — | I29: =VLOOKUP("seedance-2.0|GASIC中转|任意",费率与参数!$A$16:$G$36,6,0) -> 2 | J29: =MAX(费率与参数!$B$4,CEILING(I29/费率与参数!$B$2,费率与参数!$B$3)) -> 200 | K29: =J29*费率与参数!$B$2 -> 2 | L29: =IF(K29>0,1-I29/K29,0) -> 0
A30: Seedance 2.0 | B30: GASIC中转 | C30: doubao-seedance-2-0-260128 | D30: 1080p | E30: 任意 | F30: — | G30: 按条 | H30: — | I30: =VLOOKUP("seedance-2.0|GASIC中转|任意",费率与参数!$A$16:$G$36,6,0) -> 2 | J30: =MAX(费率与参数!$B$4,CEILING(I30/费率与参数!$B$2,费率与参数!$B$3)) -> 200 | K30: =J30*费率与参数!$B$2 -> 2 | L30: =IF(K30>0,1-I30/K30,0) -> 0
A31: Seedance 2.0 Mini（极速版） | B31: Ark官方 | C31: doubao-seedance-2-0-mini-260615 | D31: 480p | E31: 4 | F31: — | G31: token | H31: =ROUNDUP(E31*VLOOKUP(D31,费率与参数!$A$10:$D$12,2,0)*VLOOKUP(D31,费率与参数!$A$10:$D$12,3,0)*VLOOKUP(D31,费率与参数!$A$10:$D$12,4,0)/1024,0) -> 38430 | I31: =H31*VLOOKUP("seedance-2.0-mini|Ark官方|480p",费率与参数!$A$16:$G$36,6,0)/1000000 -> 0.46116 | J31: =MAX(费率与参数!$B$4,CEILING(I31/费率与参数!$B$2,费率与参数!$B$3)) -> 47 | K31: =J31*费率与参数!$B$2 -> 0.47 | L31: =IF(K31>0,1-I31/K31,0) -> 0.018808511
A32: Seedance 2.0 Mini（极速版） | B32: Ark官方 | C32: doubao-seedance-2-0-mini-260615 | D32: 480p | E32: 5 | F32: — | G32: token | H32: =ROUNDUP(E32*VLOOKUP(D32,费率与参数!$A$10:$D$12,2,0)*VLOOKUP(D32,费率与参数!$A$10:$D$12,3,0)*VLOOKUP(D32,费率与参数!$A$10:$D$12,4,0)/1024,0) -> 48038 | I32: =H32*VLOOKUP("seedance-2.0-mini|Ark官方|480p",费率与参数!$A$16:$G$36,6,0)/1000000 -> 0.576456 | J32: =MAX(费率与参数!$B$4,CEILING(I32/费率与参数!$B$2,费率与参数!$B$3)) -> 58 | K32: =J32*费率与参数!$B$2 -> 0.58 | L32: =IF(K32>0,1-I32/K32,0) -> 0.0061103448
A33: Seedance 2.0 Mini（极速版） | B33: Ark官方 | C33: doubao-seedance-2-0-mini-260615 | D33: 480p | E33: 6 | F33: — | G33: token | H33: =ROUNDUP(E33*VLOOKUP(D33,费率与参数!$A$10:$D$12,2,0)*VLOOKUP(D33,费率与参数!$A$10:$D$12,3,0)*VLOOKUP(D33,费率与参数!$A$10:$D$12,4,0)/1024,0) -> 57645 | I33: =H33*VLOOKUP("seedance-2.0-mini|Ark官方|480p",费率与参数!$A$16:$G$36,6,0)/1000000 -> 0.69174 | J33: =MAX(费率与参数!$B$4,CEILING(I33/费率与参数!$B$2,费率与参数!$B$3)) -> 70 | K33: =J33*费率与参数!$B$2 -> 0.7 | L33: =IF(K33>0,1-I33/K33,0) -> 0.0118
A34: Seedance 2.0 Mini（极速版） | B34: Ark官方 | C34: doubao-seedance-2-0-mini-260615 | D34: 480p | E34: 7 | F34: — | G34: token | H34: =ROUNDUP(E34*VLOOKUP(D34,费率与参数!$A$10:$D$12,2,0)*VLOOKUP(D34,费率与参数!$A$10:$D$12,3,0)*VLOOKUP(D34,费率与参数!$A$10:$D$12,4,0)/1024,0) -> 67253 | I34: =H34*VLOOKUP("seedance-2.0-mini|Ark官方|480p",费率与参数!$A$16:$G$36,6,0)/1000000 -> 0.807036 | J34: =MAX(费率与参数!$B$4,CEILING(I34/费率与参数!$B$2,费率与参数!$B$3)) -> 81 | K34: =J34*费率与参数!$B$2 -> 0.81 | L34: =IF(K34>0,1-I34/K34,0) -> 0.0036592593
A35: Seedance 2.0 Mini（极速版） | B35: Ark官方 | C35: doubao-seedance-2-0-mini-260615 | D35: 480p | E35: 8 | F35: — | G35: token | H35: =ROUNDUP(E35*VLOOKUP(D35,费率与参数!$A$10:$D$12,2,0)*VLOOKUP(D35,费率与参数!$A$10:$D$12,3,0)*VLOOKUP(D35,费率与参数!$A$10:$D$12,4,0)/1024,0) -> 76860 | I35: =H35*VLOOKUP("seedance-2.0-mini|Ark官方|480p",费率与参数!$A$16:$G$36,6,0)/1000000 -> 0.92232 | J35: =MAX(费率与参数!$B$4,CEILING(I35/费率与参数!$B$2,费率与参数!$B$3)) -> 93 | K35: =J35*费率与参数!$B$2 -> 0.93 | L35: =IF(K35>0,1-I35/K35,0) -> 0.0082580645
A36: Seedance 2.0 Mini（极速版） | B36: Ark官方 | C36: doubao-seedance-2-0-mini-260615 | D36: 480p | E36: 9 | F36: — | G36: token | H36: =ROUNDUP(E36*VLOOKUP(D36,费率与参数!$A$10:$D$12,2,0)*VLOOKUP(D36,费率与参数!$A$10:$D$12,3,0)*VLOOKUP(D36,费率与参数!$A$10:$D$12,4,0)/1024,0) -> 86468 | I36: =H36*VLOOKUP("seedance-2.0-mini|Ark官方|480p",费率与参数!$A$16:$G$36,6,0)/1000000 -> 1.037616 | J36: =MAX(费率与参数!$B$4,CEILING(I36/费率与参数!$B$2,费率与参数!$B$3)) -> 104 | K36: =J36*费率与参数!$B$2 -> 1.04 | L36: =IF(K36>0,1-I36/K36,0) -> 0.0022923077
A37: Seedance 2.0 Mini（极速版） | B37: Ark官方 | C37: doubao-seedance-2-0-mini-260615 | D37: 480p | E37: 10 | F37: — | G37: token | H37: =ROUNDUP(E37*VLOOKUP(D37,费率与参数!$A$10:$D$12,2,0)*VLOOKUP(D37,费率与参数!$A$10:$D$12,3,0)*VLOOKUP(D37,费率与参数!$A$10:$D$12,4,0)/1024,0) -> 96075 | I37: =H37*VLOOKUP("seedance-2.0-mini|Ark官方|480p",费率与参数!$A$16:$G$36,6,0)/1000000 -> 1.1529 | J37: =MAX(费率与参数!$B$4,CEILING(I37/费率与参数!$B$2,费率与参数!$B$3)) -> 116 | K37: =J37*费率与参数!$B$2 -> 1.16 | L37: =IF(K37>0,1-I37/K37,0) -> 0.0061206897
A38: Seedance 2.0 Mini（极速版） | B38: Ark官方 | C38: doubao-seedance-2-0-mini-260615 | D38: 480p | E38: 11 | F38: — | G38: token | H38: =ROUNDUP(E38*VLOOKUP(D38,费率与参数!$A$10:$D$12,2,0)*VLOOKUP(D38,费率与参数!$A$10:$D$12,3,0)*VLOOKUP(D38,费率与参数!$A$10:$D$12,4,0)/1024,0) -> 105683 | I38: =H38*VLOOKUP("seedance-2.0-mini|Ark官方|480p",费率与参数!$A$16:$G$36,6,0)/1000000 -> 1.268196 | J38: =MAX(费率与参数!$B$4,CEILING(I38/费率与参数!$B$2,费率与参数!$B$3)) -> 127 | K38: =J38*费率与参数!$B$2 -> 1.27 | L38: =IF(K38>0,1-I38/K38,0) -> 0.0014204724
A39: Seedance 2.0 Mini（极速版） | B39: Ark官方 | C39: doubao-seedance-2-0-mini-260615 | D39: 480p | E39: 12 | F39: — | G39: token | H39: =ROUNDUP(E39*VLOOKUP(D39,费率与参数!$A$10:$D$12,2,0)*VLOOKUP(D39,费率与参数!$A$10:$D$12,3,0)*VLOOKUP(D39,费率与参数!$A$10:$D$12,4,0)/1024,0) -> 115290 | I39: =H39*VLOOKUP("seedance-2.0-mini|Ark官方|480p",费率与参数!$A$16:$G$36,6,0)/1000000 -> 1.38348 | J39: =MAX(费率与参数!$B$4,CEILING(I39/费率与参数!$B$2,费率与参数!$B$3)) -> 139 | K39: =J39*费率与参数!$B$2 -> 1.39 | L39: =IF(K39>0,1-I39/K39,0) -> 0.0046906475
A40: Seedance 2.0 Mini（极速版） | B40: Ark官方 | C40: doubao-seedance-2-0-mini-260615 | D40: 480p | E40: 13 | F40: — | G40: token | H40: =ROUNDUP(E40*VLOOKUP(D40,费率与参数!$A$10:$D$12,2,0)*VLOOKUP(D40,费率与参数!$A$10:$D$12,3,0)*VLOOKUP(D40,费率与参数!$A$10:$D$12,4,0)/1024,0) -> 124898 | I40: =H40*VLOOKUP("seedance-2.0-mini|Ark官方|480p",费率与参数!$A$16:$G$36,6,0)/1000000 -> 1.498776 | J40: =MAX(费率与参数!$B$4,CEILING(I40/费率与参数!$B$2,费率与参数!$B$3)) -> 150 | K40: =J40*费率与参数!$B$2 -> 1.5 | L40: =IF(K40>0,1-I40/K40,0) -> 0.000816
A41: Seedance 2.0 Mini（极速版） | B41: Ark官方 | C41: doubao-seedance-2-0-mini-260615 | D41: 480p | E41: 14 | F41: — | G41: token | H41: =ROUNDUP(E41*VLOOKUP(D41,费率与参数!$A$10:$D$12,2,0)*VLOOKUP(D41,费率与参数!$A$10:$D$12,3,0)*VLOOKUP(D41,费率与参数!$A$10:$D$12,4,0)/1024,0) -> 134505 | I41: =H41*VLOOKUP("seedance-2.0-mini|Ark官方|480p",费率与参数!$A$16:$G$36,6,0)/1000000 -> 1.61406 | J41: =MAX(费率与参数!$B$4,CEILING(I41/费率与参数!$B$2,费率与参数!$B$3)) -> 162 | K41: =J41*费率与参数!$B$2 -> 1.62 | L41: =IF(K41>0,1-I41/K41,0) -> 0.0036666667
A42: Seedance 2.0 Mini（极速版） | B42: Ark官方 | C42: doubao-seedance-2-0-mini-260615 | D42: 480p | E42: 15 | F42: — | G42: token | H42: =ROUNDUP(E42*VLOOKUP(D42,费率与参数!$A$10:$D$12,2,0)*VLOOKUP(D42,费率与参数!$A$10:$D$12,3,0)*VLOOKUP(D42,费率与参数!$A$10:$D$12,4,0)/1024,0) -> 144113 | I42: =H42*VLOOKUP("seedance-2.0-mini|Ark官方|480p",费率与参数!$A$16:$G$36,6,0)/1000000 -> 1.729356 | J42: =MAX(费率与参数!$B$4,CEILING(I42/费率与参数!$B$2,费率与参数!$B$3)) -> 173 | K42: =J42*费率与参数!$B$2 -> 1.73 | L42: =IF(K42>0,1-I42/K42,0) -> 0.00037225434
A43: Seedance 2.0 Mini（极速版） | B43: Ark官方 | C43: doubao-seedance-2-0-mini-260615 | D43: 720p | E43: 4 | F43: — | G43: token | H43: =ROUNDUP(E43*VLOOKUP(D43,费率与参数!$A$10:$D$12,2,0)*VLOOKUP(D43,费率与参数!$A$10:$D$12,3,0)*VLOOKUP(D43,费率与参数!$A$10:$D$12,4,0)/1024,0) -> 86400 | I43: =H43*VLOOKUP("seedance-2.0-mini|Ark官方|720p",费率与参数!$A$16:$G$36,6,0)/1000000 -> 1.5552 | J43: =MAX(费率与参数!$B$4,CEILING(I43/费率与参数!$B$2,费率与参数!$B$3)) -> 156 | K43: =J43*费率与参数!$B$2 -> 1.56 | L43: =IF(K43>0,1-I43/K43,0) -> 0.0030769231
A44: Seedance 2.0 Mini（极速版） | B44: Ark官方 | C44: doubao-seedance-2-0-mini-260615 | D44: 720p | E44: 5 | F44: — | G44: token | H44: =ROUNDUP(E44*VLOOKUP(D44,费率与参数!$A$10:$D$12,2,0)*VLOOKUP(D44,费率与参数!$A$10:$D$12,3,0)*VLOOKUP(D44,费率与参数!$A$10:$D$12,4,0)/1024,0) -> 108000 | I44: =H44*VLOOKUP("seedance-2.0-mini|Ark官方|720p",费率与参数!$A$16:$G$36,6,0)/1000000 -> 1.944 | J44: =MAX(费率与参数!$B$4,CEILING(I44/费率与参数!$B$2,费率与参数!$B$3)) -> 195 | K44: =J44*费率与参数!$B$2 -> 1.95 | L44: =IF(K44>0,1-I44/K44,0) -> 0.0030769231
A45: Seedance 2.0 Mini（极速版） | B45: Ark官方 | C45: doubao-seedance-2-0-mini-260615 | D45: 720p | E45: 6 | F45: — | G45: token | H45: =ROUNDUP(E45*VLOOKUP(D45,费率与参数!$A$10:$D$12,2,0)*VLOOKUP(D45,费率与参数!$A$10:$D$12,3,0)*VLOOKUP(D45,费率与参数!$A$10:$D$12,4,0)/1024,0) -> 129600 | I45: =H45*VLOOKUP("seedance-2.0-mini|Ark官方|720p",费率与参数!$A$16:$G$36,6,0)/1000000 -> 2.3328 | J45: =MAX(费率与参数!$B$4,CEILING(I45/费率与参数!$B$2,费率与参数!$B$3)) -> 234 | K45: =J45*费率与参数!$B$2 -> 2.34 | L45: =IF(K45>0,1-I45/K45,0) -> 0.0030769231
A46: Seedance 2.0 Mini（极速版） | B46: Ark官方 | C46: doubao-seedance-2-0-mini-260615 | D46: 720p | E46: 7 | F46: — | G46: token | H46: =ROUNDUP(E46*VLOOKUP(D46,费率与参数!$A$10:$D$12,2,0)*VLOOKUP(D46,费率与参数!$A$10:$D$12,3,0)*VLOOKUP(D46,费率与参数!$A$10:$D$12,4,0)/1024,0) -> 151200 | I46: =H46*VLOOKUP("seedance-2.0-mini|Ark官方|720p",费率与参数!$A$16:$G$36,6,0)/1000000 -> 2.7216 | J46: =MAX(费率与参数!$B$4,CEILING(I46/费率与参数!$B$2,费率与参数!$B$3)) -> 273 | K46: =J46*费率与参数!$B$2 -> 2.73 | L46: =IF(K46>0,1-I46/K46,0) -> 0.0030769231
A47: Seedance 2.0 Mini（极速版） | B47: Ark官方 | C47: doubao-seedance-2-0-mini-260615 | D47: 720p | E47: 8 | F47: — | G47: token | H47: =ROUNDUP(E47*VLOOKUP(D47,费率与参数!$A$10:$D$12,2,0)*VLOOKUP(D47,费率与参数!$A$10:$D$12,3,0)*VLOOKUP(D47,费率与参数!$A$10:$D$12,4,0)/1024,0) -> 172800 | I47: =H47*VLOOKUP("seedance-2.0-mini|Ark官方|720p",费率与参数!$A$16:$G$36,6,0)/1000000 -> 3.1104 | J47: =MAX(费率与参数!$B$4,CEILING(I47/费率与参数!$B$2,费率与参数!$B$3)) -> 312 | K47: =J47*费率与参数!$B$2 -> 3.12 | L47: =IF(K47>0,1-I47/K47,0) -> 0.0030769231
A48: Seedance 2.0 Mini（极速版） | B48: Ark官方 | C48: doubao-seedance-2-0-mini-260615 | D48: 720p | E48: 9 | F48: — | G48: token | H48: =ROUNDUP(E48*VLOOKUP(D48,费率与参数!$A$10:$D$12,2,0)*VLOOKUP(D48,费率与参数!$A$10:$D$12,3,0)*VLOOKUP(D48,费率与参数!$A$10:$D$12,4,0)/1024,0) -> 194400 | I48: =H48*VLOOKUP("seedance-2.0-mini|Ark官方|720p",费率与参数!$A$16:$G$36,6,0)/1000000 -> 3.4992 | J48: =MAX(费率与参数!$B$4,CEILING(I48/费率与参数!$B$2,费率与参数!$B$3)) -> 350 | K48: =J48*费率与参数!$B$2 -> 3.5 | L48: =IF(K48>0,1-I48/K48,0) -> 0.00022857143
A49: Seedance 2.0 Mini（极速版） | B49: Ark官方 | C49: doubao-seedance-2-0-mini-260615 | D49: 720p | E49: 10 | F49: — | G49: token | H49: =ROUNDUP(E49*VLOOKUP(D49,费率与参数!$A$10:$D$12,2,0)*VLOOKUP(D49,费率与参数!$A$10:$D$12,3,0)*VLOOKUP(D49,费率与参数!$A$10:$D$12,4,0)/1024,0) -> 216000 | I49: =H49*VLOOKUP("seedance-2.0-mini|Ark官方|720p",费率与参数!$A$16:$G$36,6,0)/1000000 -> 3.888 | J49: =MAX(费率与参数!$B$4,CEILING(I49/费率与参数!$B$2,费率与参数!$B$3)) -> 389 | K49: =J49*费率与参数!$B$2 -> 3.89 | L49: =IF(K49>0,1-I49/K49,0) -> 0.00051413882
A50: Seedance 2.0 Mini（极速版） | B50: Ark官方 | C50: doubao-seedance-2-0-mini-260615 | D50: 720p | E50: 11 | F50: — | G50: token | H50: =ROUNDUP(E50*VLOOKUP(D50,费率与参数!$A$10:$D$12,2,0)*VLOOKUP(D50,费率与参数!$A$10:$D$12,3,0)*VLOOKUP(D50,费率与参数!$A$10:$D$12,4,0)/1024,0) -> 237600 | I50: =H50*VLOOKUP("seedance-2.0-mini|Ark官方|720p",费率与参数!$A$16:$G$36,6,0)/1000000 -> 4.2768 | J50: =MAX(费率与参数!$B$4,CEILING(I50/费率与参数!$B$2,费率与参数!$B$3)) -> 428 | K50: =J50*费率与参数!$B$2 -> 4.28 | L50: =IF(K50>0,1-I50/K50,0) -> 0.00074766355
A51: Seedance 2.0 Mini（极速版） | B51: Ark官方 | C51: doubao-seedance-2-0-mini-260615 | D51: 720p | E51: 12 | F51: — | G51: token | H51: =ROUNDUP(E51*VLOOKUP(D51,费率与参数!$A$10:$D$12,2,0)*VLOOKUP(D51,费率与参数!$A$10:$D$12,3,0)*VLOOKUP(D51,费率与参数!$A$10:$D$12,4,0)/1024,0) -> 259200 | I51: =H51*VLOOKUP("seedance-2.0-mini|Ark官方|720p",费率与参数!$A$16:$G$36,6,0)/1000000 -> 4.6656 | J51: =MAX(费率与参数!$B$4,CEILING(I51/费率与参数!$B$2,费率与参数!$B$3)) -> 467 | K51: =J51*费率与参数!$B$2 -> 4.67 | L51: =IF(K51>0,1-I51/K51,0) -> 0.00094218415
A52: Seedance 2.0 Mini（极速版） | B52: Ark官方 | C52: doubao-seedance-2-0-mini-260615 | D52: 720p | E52: 13 | F52: — | G52: token | H52: =ROUNDUP(E52*VLOOKUP(D52,费率与参数!$A$10:$D$12,2,0)*VLOOKUP(D52,费率与参数!$A$10:$D$12,3,0)*VLOOKUP(D52,费率与参数!$A$10:$D$12,4,0)/1024,0) -> 280800 | I52: =H52*VLOOKUP("seedance-2.0-mini|Ark官方|720p",费率与参数!$A$16:$G$36,6,0)/1000000 -> 5.0544 | J52: =MAX(费率与参数!$B$4,CEILING(I52/费率与参数!$B$2,费率与参数!$B$3)) -> 506 | K52: =J52*费率与参数!$B$2 -> 5.06 | L52: =IF(K52>0,1-I52/K52,0) -> 0.0011067194
A53: Seedance 2.0 Mini（极速版） | B53: Ark官方 | C53: doubao-seedance-2-0-mini-260615 | D53: 720p | E53: 14 | F53: — | G53: token | H53: =ROUNDUP(E53*VLOOKUP(D53,费率与参数!$A$10:$D$12,2,0)*VLOOKUP(D53,费率与参数!$A$10:$D$12,3,0)*VLOOKUP(D53,费率与参数!$A$10:$D$12,4,0)/1024,0) -> 302400 | I53: =H53*VLOOKUP("seedance-2.0-mini|Ark官方|720p",费率与参数!$A$16:$G$36,6,0)/1000000 -> 5.4432 | J53: =MAX(费率与参数!$B$4,CEILING(I53/费率与参数!$B$2,费率与参数!$B$3)) -> 545 | K53: =J53*费率与参数!$B$2 -> 5.45 | L53: =IF(K53>0,1-I53/K53,0) -> 0.0012477064
A54: Seedance 2.0 Mini（极速版） | B54: Ark官方 | C54: doubao-seedance-2-0-mini-260615 | D54: 720p | E54: 15 | F54: — | G54: token | H54: =ROUNDUP(E54*VLOOKUP(D54,费率与参数!$A$10:$D$12,2,0)*VLOOKUP(D54,费率与参数!$A$10:$D$12,3,0)*VLOOKUP(D54,费率与参数!$A$10:$D$12,4,0)/1024,0) -> 324000 | I54: =H54*VLOOKUP("seedance-2.0-mini|Ark官方|720p",费率与参数!$A$16:$G$36,6,0)/1000000 -> 5.832 | J54: =MAX(费率与参数!$B$4,CEILING(I54/费率与参数!$B$2,费率与参数!$B$3)) -> 584 | K54: =J54*费率与参数!$B$2 -> 5.84 | L54: =IF(K54>0,1-I54/K54,0) -> 0.001369863
A55: Seedance 2.0 Mini（极速版） | B55: Ark官方 | C55: doubao-seedance-2-0-mini-260615 | D55: 1080p | E55: 4 | F55: — | G55: token | H55: =ROUNDUP(E55*VLOOKUP(D55,费率与参数!$A$10:$D$12,2,0)*VLOOKUP(D55,费率与参数!$A$10:$D$12,3,0)*VLOOKUP(D55,费率与参数!$A$10:$D$12,4,0)/1024,0) -> 194400 | I55: =H55*VLOOKUP("seedance-2.0-mini|Ark官方|1080p",费率与参数!$A$16:$G$36,6,0)/1000000 -> 5.832 | J55: =MAX(费率与参数!$B$4,CEILING(I55/费率与参数!$B$2,费率与参数!$B$3)) -> 584 | K55: =J55*费率与参数!$B$2 -> 5.84 | L55: =IF(K55>0,1-I55/K55,0) -> 0.001369863
A56: Seedance 2.0 Mini（极速版） | B56: Ark官方 | C56: doubao-seedance-2-0-mini-260615 | D56: 1080p | E56: 5 | F56: — | G56: token | H56: =ROUNDUP(E56*VLOOKUP(D56,费率与参数!$A$10:$D$12,2,0)*VLOOKUP(D56,费率与参数!$A$10:$D$12,3,0)*VLOOKUP(D56,费率与参数!$A$10:$D$12,4,0)/1024,0) -> 243000 | I56: =H56*VLOOKUP("seedance-2.0-mini|Ark官方|1080p",费率与参数!$A$16:$G$36,6,0)/1000000 -> 7.29 | J56: =MAX(费率与参数!$B$4,CEILING(I56/费率与参数!$B$2,费率与参数!$B$3)) -> 729 | K56: =J56*费率与参数!$B$2 -> 7.29 | L56: =IF(K56>0,1-I56/K56,0) -> 0
A57: Seedance 2.0 Mini（极速版） | B57: Ark官方 | C57: doubao-seedance-2-0-mini-260615 | D57: 1080p | E57: 6 | F57: — | G57: token | H57: =ROUNDUP(E57*VLOOKUP(D57,费率与参数!$A$10:$D$12,2,0)*VLOOKUP(D57,费率与参数!$A$10:$D$12,3,0)*VLOOKUP(D57,费率与参数!$A$10:$D$12,4,0)/1024,0) -> 291600 | I57: =H57*VLOOKUP("seedance-2.0-mini|Ark官方|1080p",费率与参数!$A$16:$G$36,6,0)/1000000 -> 8.748 | J57: =MAX(费率与参数!$B$4,CEILING(I57/费率与参数!$B$2,费率与参数!$B$3)) -> 875 | K57: =J57*费率与参数!$B$2 -> 8.75 | L57: =IF(K57>0,1-I57/K57,0) -> 0.00022857143
A58: Seedance 2.0 Mini（极速版） | B58: Ark官方 | C58: doubao-seedance-2-0-mini-260615 | D58: 1080p | E58: 7 | F58: — | G58: token | H58: =ROUNDUP(E58*VLOOKUP(D58,费率与参数!$A$10:$D$12,2,0)*VLOOKUP(D58,费率与参数!$A$10:$D$12,3,0)*VLOOKUP(D58,费率与参数!$A$10:$D$12,4,0)/1024,0) -> 340200 | I58: =H58*VLOOKUP("seedance-2.0-mini|Ark官方|1080p",费率与参数!$A$16:$G$36,6,0)/1000000 -> 10.206 | J58: =MAX(费率与参数!$B$4,CEILING(I58/费率与参数!$B$2,费率与参数!$B$3)) -> 1021 | K58: =J58*费率与参数!$B$2 -> 10.21 | L58: =IF(K58>0,1-I58/K58,0) -> 0.00039177277
A59: Seedance 2.0 Mini（极速版） | B59: Ark官方 | C59: doubao-seedance-2-0-mini-260615 | D59: 1080p | E59: 8 | F59: — | G59: token | H59: =ROUNDUP(E59*VLOOKUP(D59,费率与参数!$A$10:$D$12,2,0)*VLOOKUP(D59,费率与参数!$A$10:$D$12,3,0)*VLOOKUP(D59,费率与参数!$A$10:$D$12,4,0)/1024,0) -> 388800 | I59: =H59*VLOOKUP("seedance-2.0-mini|Ark官方|1080p",费率与参数!$A$16:$G$36,6,0)/1000000 -> 11.664 | J59: =MAX(费率与参数!$B$4,CEILING(I59/费率与参数!$B$2,费率与参数!$B$3)) -> 1167 | K59: =J59*费率与参数!$B$2 -> 11.67 | L59: =IF(K59>0,1-I59/K59,0) -> 0.00051413882
A60: Seedance 2.0 Mini（极速版） | B60: Ark官方 | C60: doubao-seedance-2-0-mini-260615 | D60: 1080p | E60: 9 | F60: — | G60: token | H60: =ROUNDUP(E60*VLOOKUP(D60,费率与参数!$A$10:$D$12,2,0)*VLOOKUP(D60,费率与参数!$A$10:$D$12,3,0)*VLOOKUP(D60,费率与参数!$A$10:$D$12,4,0)/1024,0) -> 437400 | I60: =H60*VLOOKUP("seedance-2.0-mini|Ark官方|1080p",费率与参数!$A$16:$G$36,6,0)/1000000 -> 13.122 | J60: =MAX(费率与参数!$B$4,CEILING(I60/费率与参数!$B$2,费率与参数!$B$3)) -> 1313 | K60: =J60*费率与参数!$B$2 -> 13.13 | L60: =IF(K60>0,1-I60/K60,0) -> 0.0006092917
A61: Seedance 2.0 Mini（极速版） | B61: Ark官方 | C61: doubao-seedance-2-0-mini-260615 | D61: 1080p | E61: 10 | F61: — | G61: token | H61: =ROUNDUP(E61*VLOOKUP(D61,费率与参数!$A$10:$D$12,2,0)*VLOOKUP(D61,费率与参数!$A$10:$D$12,3,0)*VLOOKUP(D61,费率与参数!$A$10:$D$12,4,0)/1024,0) -> 486000 | I61: =H61*VLOOKUP("seedance-2.0-mini|Ark官方|1080p",费率与参数!$A$16:$G$36,6,0)/1000000 -> 14.58 | J61: =MAX(费率与参数!$B$4,CEILING(I61/费率与参数!$B$2,费率与参数!$B$3)) -> 1458 | K61: =J61*费率与参数!$B$2 -> 14.58 | L61: =IF(K61>0,1-I61/K61,0) -> 0
A62: Seedance 2.0 Mini（极速版） | B62: Ark官方 | C62: doubao-seedance-2-0-mini-260615 | D62: 1080p | E62: 11 | F62: — | G62: token | H62: =ROUNDUP(E62*VLOOKUP(D62,费率与参数!$A$10:$D$12,2,0)*VLOOKUP(D62,费率与参数!$A$10:$D$12,3,0)*VLOOKUP(D62,费率与参数!$A$10:$D$12,4,0)/1024,0) -> 534600 | I62: =H62*VLOOKUP("seedance-2.0-mini|Ark官方|1080p",费率与参数!$A$16:$G$36,6,0)/1000000 -> 16.038 | J62: =MAX(费率与参数!$B$4,CEILING(I62/费率与参数!$B$2,费率与参数!$B$3)) -> 1604 | K62: =J62*费率与参数!$B$2 -> 16.04 | L62: =IF(K62>0,1-I62/K62,0) -> 0.00012468828
A63: Seedance 2.0 Mini（极速版） | B63: Ark官方 | C63: doubao-seedance-2-0-mini-260615 | D63: 1080p | E63: 12 | F63: — | G63: token | H63: =ROUNDUP(E63*VLOOKUP(D63,费率与参数!$A$10:$D$12,2,0)*VLOOKUP(D63,费率与参数!$A$10:$D$12,3,0)*VLOOKUP(D63,费率与参数!$A$10:$D$12,4,0)/1024,0) -> 583200 | I63: =H63*VLOOKUP("seedance-2.0-mini|Ark官方|1080p",费率与参数!$A$16:$G$36,6,0)/1000000 -> 17.496 | J63: =MAX(费率与参数!$B$4,CEILING(I63/费率与参数!$B$2,费率与参数!$B$3)) -> 1750 | K63: =J63*费率与参数!$B$2 -> 17.5 | L63: =IF(K63>0,1-I63/K63,0) -> 0.00022857143
A64: Seedance 2.0 Mini（极速版） | B64: Ark官方 | C64: doubao-seedance-2-0-mini-260615 | D64: 1080p | E64: 13 | F64: — | G64: token | H64: =ROUNDUP(E64*VLOOKUP(D64,费率与参数!$A$10:$D$12,2,0)*VLOOKUP(D64,费率与参数!$A$10:$D$12,3,0)*VLOOKUP(D64,费率与参数!$A$10:$D$12,4,0)/1024,0) -> 631800 | I64: =H64*VLOOKUP("seedance-2.0-mini|Ark官方|1080p",费率与参数!$A$16:$G$36,6,0)/1000000 -> 18.954 | J64: =MAX(费率与参数!$B$4,CEILING(I64/费率与参数!$B$2,费率与参数!$B$3)) -> 1896 | K64: =J64*费率与参数!$B$2 -> 18.96 | L64: =IF(K64>0,1-I64/K64,0) -> 0.0003164557
A65: Seedance 2.0 Mini（极速版） | B65: Ark官方 | C65: doubao-seedance-2-0-mini-260615 | D65: 1080p | E65: 14 | F65: — | G65: token | H65: =ROUNDUP(E65*VLOOKUP(D65,费率与参数!$A$10:$D$12,2,0)*VLOOKUP(D65,费率与参数!$A$10:$D$12,3,0)*VLOOKUP(D65,费率与参数!$A$10:$D$12,4,0)/1024,0) -> 680400 | I65: =H65*VLOOKUP("seedance-2.0-mini|Ark官方|1080p",费率与参数!$A$16:$G$36,6,0)/1000000 -> 20.412 | J65: =MAX(费率与参数!$B$4,CEILING(I65/费率与参数!$B$2,费率与参数!$B$3)) -> 2042 | K65: =J65*费率与参数!$B$2 -> 20.42 | L65: =IF(K65>0,1-I65/K65,0) -> 0.00039177277
A66: Seedance 2.0 Mini（极速版） | B66: Ark官方 | C66: doubao-seedance-2-0-mini-260615 | D66: 1080p | E66: 15 | F66: — | G66: token | H66: =ROUNDUP(E66*VLOOKUP(D66,费率与参数!$A$10:$D$12,2,0)*VLOOKUP(D66,费率与参数!$A$10:$D$12,3,0)*VLOOKUP(D66,费率与参数!$A$10:$D$12,4,0)/1024,0) -> 729000 | I66: =H66*VLOOKUP("seedance-2.0-mini|Ark官方|1080p",费率与参数!$A$16:$G$36,6,0)/1000000 -> 21.87 | J66: =MAX(费率与参数!$B$4,CEILING(I66/费率与参数!$B$2,费率与参数!$B$3)) -> 2187 | K66: =J66*费率与参数!$B$2 -> 21.87 | L66: =IF(K66>0,1-I66/K66,0) -> 0
A67: MiniMax H3（海螺） | B67: MiniMax官方 | C67: MiniMax-H3 | D67: 768p | E67: 4 | F67: 0 | G67: 每秒 | H67: — | I67: =E67*VLOOKUP("minimax-h3|MiniMax官方|768p",费率与参数!$A$16:$G$36,6,0) -> 2 | J67: =MAX(费率与参数!$B$4,CEILING(I67/费率与参数!$B$2,费率与参数!$B$3)) -> 200 | K67: =J67*费率与参数!$B$2 -> 2 | L67: =IF(K67>0,1-I67/K67,0) -> 0
A68: MiniMax H3（海螺） | B68: MiniMax官方 | C68: MiniMax-H3 | D68: 768p | E68: 5 | F68: 0 | G68: 每秒 | H68: — | I68: =E68*VLOOKUP("minimax-h3|MiniMax官方|768p",费率与参数!$A$16:$G$36,6,0) -> 2.5 | J68: =MAX(费率与参数!$B$4,CEILING(I68/费率与参数!$B$2,费率与参数!$B$3)) -> 250 | K68: =J68*费率与参数!$B$2 -> 2.5 | L68: =IF(K68>0,1-I68/K68,0) -> 0
A69: MiniMax H3（海螺） | B69: MiniMax官方 | C69: MiniMax-H3 | D69: 768p | E69: 6 | F69: 0 | G69: 每秒 | H69: — | I69: =E69*VLOOKUP("minimax-h3|MiniMax官方|768p",费率与参数!$A$16:$G$36,6,0) -> 3 | J69: =MAX(费率与参数!$B$4,CEILING(I69/费率与参数!$B$2,费率与参数!$B$3)) -> 300 | K69: =J69*费率与参数!$B$2 -> 3 | L69: =IF(K69>0,1-I69/K69,0) -> 0
A70: MiniMax H3（海螺） | B70: MiniMax官方 | C70: MiniMax-H3 | D70: 768p | E70: 7 | F70: 0 | G70: 每秒 | H70: — | I70: =E70*VLOOKUP("minimax-h3|MiniMax官方|768p",费率与参数!$A$16:$G$36,6,0) -> 3.5 | J70: =MAX(费率与参数!$B$4,CEILING(I70/费率与参数!$B$2,费率与参数!$B$3)) -> 350 | K70: =J70*费率与参数!$B$2 -> 3.5 | L70: =IF(K70>0,1-I70/K70,0) -> 0
A71: MiniMax H3（海螺） | B71: MiniMax官方 | C71: MiniMax-H3 | D71: 768p | E71: 8 | F71: 0 | G71: 每秒 | H71: — | I71: =E71*VLOOKUP("minimax-h3|MiniMax官方|768p",费率与参数!$A$16:$G$36,6,0) -> 4 | J71: =MAX(费率与参数!$B$4,CEILING(I71/费率与参数!$B$2,费率与参数!$B$3)) -> 400 | K71: =J71*费率与参数!$B$2 -> 4 | L71: =IF(K71>0,1-I71/K71,0) -> 0
A72: MiniMax H3（海螺） | B72: MiniMax官方 | C72: MiniMax-H3 | D72: 768p | E72: 9 | F72: 0 | G72: 每秒 | H72: — | I72: =E72*VLOOKUP("minimax-h3|MiniMax官方|768p",费率与参数!$A$16:$G$36,6,0) -> 4.5 | J72: =MAX(费率与参数!$B$4,CEILING(I72/费率与参数!$B$2,费率与参数!$B$3)) -> 450 | K72: =J72*费率与参数!$B$2 -> 4.5 | L72: =IF(K72>0,1-I72/K72,0) -> 0
A73: MiniMax H3（海螺） | B73: MiniMax官方 | C73: MiniMax-H3 | D73: 768p | E73: 10 | F73: 0 | G73: 每秒 | H73: — | I73: =E73*VLOOKUP("minimax-h3|MiniMax官方|768p",费率与参数!$A$16:$G$36,6,0) -> 5 | J73: =MAX(费率与参数!$B$4,CEILING(I73/费率与参数!$B$2,费率与参数!$B$3)) -> 500 | K73: =J73*费率与参数!$B$2 -> 5 | L73: =IF(K73>0,1-I73/K73,0) -> 0
A74: MiniMax H3（海螺） | B74: MiniMax官方 | C74: MiniMax-H3 | D74: 768p | E74: 11 | F74: 0 | G74: 每秒 | H74: — | I74: =E74*VLOOKUP("minimax-h3|MiniMax官方|768p",费率与参数!$A$16:$G$36,6,0) -> 5.5 | J74: =MAX(费率与参数!$B$4,CEILING(I74/费率与参数!$B$2,费率与参数!$B$3)) -> 550 | K74: =J74*费率与参数!$B$2 -> 5.5 | L74: =IF(K74>0,1-I74/K74,0) -> 0
A75: MiniMax H3（海螺） | B75: MiniMax官方 | C75: MiniMax-H3 | D75: 768p | E75: 12 | F75: 0 | G75: 每秒 | H75: — | I75: =E75*VLOOKUP("minimax-h3|MiniMax官方|768p",费率与参数!$A$16:$G$36,6,0) -> 6 | J75: =MAX(费率与参数!$B$4,CEILING(I75/费率与参数!$B$2,费率与参数!$B$3)) -> 600 | K75: =J75*费率与参数!$B$2 -> 6 | L75: =IF(K75>0,1-I75/K75,0) -> 0
A76: MiniMax H3（海螺） | B76: MiniMax官方 | C76: MiniMax-H3 | D76: 768p | E76: 13 | F76: 0 | G76: 每秒 | H76: — | I76: =E76*VLOOKUP("minimax-h3|MiniMax官方|768p",费率与参数!$A$16:$G$36,6,0) -> 6.5 | J76: =MAX(费率与参数!$B$4,CEILING(I76/费率与参数!$B$2,费率与参数!$B$3)) -> 650 | K76: =J76*费率与参数!$B$2 -> 6.5 | L76: =IF(K76>0,1-I76/K76,0) -> 0
A77: MiniMax H3（海螺） | B77: MiniMax官方 | C77: MiniMax-H3 | D77: 768p | E77: 14 | F77: 0 | G77: 每秒 | H77: — | I77: =E77*VLOOKUP("minimax-h3|MiniMax官方|768p",费率与参数!$A$16:$G$36,6,0) -> 7 | J77: =MAX(费率与参数!$B$4,CEILING(I77/费率与参数!$B$2,费率与参数!$B$3)) -> 700 | K77: =J77*费率与参数!$B$2 -> 7 | L77: =IF(K77>0,1-I77/K77,0) -> 0
A78: MiniMax H3（海螺） | B78: MiniMax官方 | C78: MiniMax-H3 | D78: 768p | E78: 15 | F78: 0 | G78: 每秒 | H78: — | I78: =E78*VLOOKUP("minimax-h3|MiniMax官方|768p",费率与参数!$A$16:$G$36,6,0) -> 7.5 | J78: =MAX(费率与参数!$B$4,CEILING(I78/费率与参数!$B$2,费率与参数!$B$3)) -> 750 | K78: =J78*费率与参数!$B$2 -> 7.5 | L78: =IF(K78>0,1-I78/K78,0) -> 0
A79: MiniMax H3（海螺） | B79: MiniMax官方 | C79: MiniMax-H3 | D79: 2k | E79: 4 | F79: 0 | G79: 每秒 | H79: — | I79: =E79*VLOOKUP("minimax-h3|MiniMax官方|2k",费率与参数!$A$16:$G$36,6,0) -> 3.2 | J79: =MAX(费率与参数!$B$4,CEILING(I79/费率与参数!$B$2,费率与参数!$B$3)) -> 320 | K79: =J79*费率与参数!$B$2 -> 3.2 | L79: =IF(K79>0,1-I79/K79,0) -> 0
A80: MiniMax H3（海螺） | B80: MiniMax官方 | C80: MiniMax-H3 | D80: 2k | E80: 5 | F80: 0 | G80: 每秒 | H80: — | I80: =E80*VLOOKUP("minimax-h3|MiniMax官方|2k",费率与参数!$A$16:$G$36,6,0) -> 4 | J80: =MAX(费率与参数!$B$4,CEILING(I80/费率与参数!$B$2,费率与参数!$B$3)) -> 400 | K80: =J80*费率与参数!$B$2 -> 4 | L80: =IF(K80>0,1-I80/K80,0) -> 0
A81: MiniMax H3（海螺） | B81: MiniMax官方 | C81: MiniMax-H3 | D81: 2k | E81: 6 | F81: 0 | G81: 每秒 | H81: — | I81: =E81*VLOOKUP("minimax-h3|MiniMax官方|2k",费率与参数!$A$16:$G$36,6,0) -> 4.8 | J81: =MAX(费率与参数!$B$4,CEILING(I81/费率与参数!$B$2,费率与参数!$B$3)) -> 480 | K81: =J81*费率与参数!$B$2 -> 4.8 | L81: =IF(K81>0,1-I81/K81,0) -> 0
A82: MiniMax H3（海螺） | B82: MiniMax官方 | C82: MiniMax-H3 | D82: 2k | E82: 7 | F82: 0 | G82: 每秒 | H82: — | I82: =E82*VLOOKUP("minimax-h3|MiniMax官方|2k",费率与参数!$A$16:$G$36,6,0) -> 5.6 | J82: =MAX(费率与参数!$B$4,CEILING(I82/费率与参数!$B$2,费率与参数!$B$3)) -> 560 | K82: =J82*费率与参数!$B$2 -> 5.6 | L82: =IF(K82>0,1-I82/K82,0) -> 0
A83: MiniMax H3（海螺） | B83: MiniMax官方 | C83: MiniMax-H3 | D83: 2k | E83: 8 | F83: 0 | G83: 每秒 | H83: — | I83: =E83*VLOOKUP("minimax-h3|MiniMax官方|2k",费率与参数!$A$16:$G$36,6,0) -> 6.4 | J83: =MAX(费率与参数!$B$4,CEILING(I83/费率与参数!$B$2,费率与参数!$B$3)) -> 640 | K83: =J83*费率与参数!$B$2 -> 6.4 | L83: =IF(K83>0,1-I83/K83,0) -> 0
A84: MiniMax H3（海螺） | B84: MiniMax官方 | C84: MiniMax-H3 | D84: 2k | E84: 9 | F84: 0 | G84: 每秒 | H84: — | I84: =E84*VLOOKUP("minimax-h3|MiniMax官方|2k",费率与参数!$A$16:$G$36,6,0) -> 7.2 | J84: =MAX(费率与参数!$B$4,CEILING(I84/费率与参数!$B$2,费率与参数!$B$3)) -> 720 | K84: =J84*费率与参数!$B$2 -> 7.2 | L84: =IF(K84>0,1-I84/K84,0) -> 0
A85: MiniMax H3（海螺） | B85: MiniMax官方 | C85: MiniMax-H3 | D85: 2k | E85: 10 | F85: 0 | G85: 每秒 | H85: — | I85: =E85*VLOOKUP("minimax-h3|MiniMax官方|2k",费率与参数!$A$16:$G$36,6,0) -> 8 | J85: =MAX(费率与参数!$B$4,CEILING(I85/费率与参数!$B$2,费率与参数!$B$3)) -> 800 | K85: =J85*费率与参数!$B$2 -> 8 | L85: =IF(K85>0,1-I85/K85,0) -> 0
A86: MiniMax H3（海螺） | B86: MiniMax官方 | C86: MiniMax-H3 | D86: 2k | E86: 11 | F86: 0 | G86: 每秒 | H86: — | I86: =E86*VLOOKUP("minimax-h3|MiniMax官方|2k",费率与参数!$A$16:$G$36,6,0) -> 8.8 | J86: =MAX(费率与参数!$B$4,CEILING(I86/费率与参数!$B$2,费率与参数!$B$3)) -> 880 | K86: =J86*费率与参数!$B$2 -> 8.8 | L86: =IF(K86>0,1-I86/K86,0) -> 0
A87: MiniMax H3（海螺） | B87: MiniMax官方 | C87: MiniMax-H3 | D87: 2k | E87: 12 | F87: 0 | G87: 每秒 | H87: — | I87: =E87*VLOOKUP("minimax-h3|MiniMax官方|2k",费率与参数!$A$16:$G$36,6,0) -> 9.6 | J87: =MAX(费率与参数!$B$4,CEILING(I87/费率与参数!$B$2,费率与参数!$B$3)) -> 960 | K87: =J87*费率与参数!$B$2 -> 9.6 | L87: =IF(K87>0,1-I87/K87,0) -> 0
A88: MiniMax H3（海螺） | B88: MiniMax官方 | C88: MiniMax-H3 | D88: 2k | E88: 13 | F88: 0 | G88: 每秒 | H88: — | I88: =E88*VLOOKUP("minimax-h3|MiniMax官方|2k",费率与参数!$A$16:$G$36,6,0) -> 10.4 | J88: =MAX(费率与参数!$B$4,CEILING(I88/费率与参数!$B$2,费率与参数!$B$3)) -> 1040 | K88: =J88*费率与参数!$B$2 -> 10.4 | L88: =IF(K88>0,1-I88/K88,0) -> 0
A89: MiniMax H3（海螺） | B89: MiniMax官方 | C89: MiniMax-H3 | D89: 2k | E89: 14 | F89: 0 | G89: 每秒 | H89: — | I89: =E89*VLOOKUP("minimax-h3|MiniMax官方|2k",费率与参数!$A$16:$G$36,6,0) -> 11.2 | J89: =MAX(费率与参数!$B$4,CEILING(I89/费率与参数!$B$2,费率与参数!$B$3)) -> 1120 | K89: =J89*费率与参数!$B$2 -> 11.2 | L89: =IF(K89>0,1-I89/K89,0) -> 0
A90: MiniMax H3（海螺） | B90: MiniMax官方 | C90: MiniMax-H3 | D90: 2k | E90: 15 | F90: 0 | G90: 每秒 | H90: — | I90: =E90*VLOOKUP("minimax-h3|MiniMax官方|2k",费率与参数!$A$16:$G$36,6,0) -> 12 | J90: =MAX(费率与参数!$B$4,CEILING(I90/费率与参数!$B$2,费率与参数!$B$3)) -> 1200 | K90: =J90*费率与参数!$B$2 -> 12 | L90: =IF(K90>0,1-I90/K90,0) -> 0
A91: MiniMax H3-Max（海螺） | B91: MiniMax官方 | C91: MiniMax-H3-Max | D91: 480p | E91: 5 | F91: 0 | G91: 每秒 | H91: — | I91: =E91*VLOOKUP("minimax-h3-max|MiniMax官方|480p",费率与参数!$A$16:$G$36,6,0) -> 2.5 | J91: =MAX(费率与参数!$B$4,CEILING(I91/费率与参数!$B$2,费率与参数!$B$3)) -> 250 | K91: =J91*费率与参数!$B$2 -> 2.5 | L91: =IF(K91>0,1-I91/K91,0) -> 0
A92: MiniMax H3-Max（海螺） | B92: MiniMax官方 | C92: MiniMax-H3-Max | D92: 480p | E92: 6 | F92: 0 | G92: 每秒 | H92: — | I92: =E92*VLOOKUP("minimax-h3-max|MiniMax官方|480p",费率与参数!$A$16:$G$36,6,0) -> 3 | J92: =MAX(费率与参数!$B$4,CEILING(I92/费率与参数!$B$2,费率与参数!$B$3)) -> 300 | K92: =J92*费率与参数!$B$2 -> 3 | L92: =IF(K92>0,1-I92/K92,0) -> 0
A93: MiniMax H3-Max（海螺） | B93: MiniMax官方 | C93: MiniMax-H3-Max | D93: 480p | E93: 7 | F93: 0 | G93: 每秒 | H93: — | I93: =E93*VLOOKUP("minimax-h3-max|MiniMax官方|480p",费率与参数!$A$16:$G$36,6,0) -> 3.5 | J93: =MAX(费率与参数!$B$4,CEILING(I93/费率与参数!$B$2,费率与参数!$B$3)) -> 350 | K93: =J93*费率与参数!$B$2 -> 3.5 | L93: =IF(K93>0,1-I93/K93,0) -> 0
A94: MiniMax H3-Max（海螺） | B94: MiniMax官方 | C94: MiniMax-H3-Max | D94: 480p | E94: 8 | F94: 0 | G94: 每秒 | H94: — | I94: =E94*VLOOKUP("minimax-h3-max|MiniMax官方|480p",费率与参数!$A$16:$G$36,6,0) -> 4 | J94: =MAX(费率与参数!$B$4,CEILING(I94/费率与参数!$B$2,费率与参数!$B$3)) -> 400 | K94: =J94*费率与参数!$B$2 -> 4 | L94: =IF(K94>0,1-I94/K94,0) -> 0
A95: MiniMax H3-Max（海螺） | B95: MiniMax官方 | C95: MiniMax-H3-Max | D95: 480p | E95: 9 | F95: 0 | G95: 每秒 | H95: — | I95: =E95*VLOOKUP("minimax-h3-max|MiniMax官方|480p",费率与参数!$A$16:$G$36,6,0) -> 4.5 | J95: =MAX(费率与参数!$B$4,CEILING(I95/费率与参数!$B$2,费率与参数!$B$3)) -> 450 | K95: =J95*费率与参数!$B$2 -> 4.5 | L95: =IF(K95>0,1-I95/K95,0) -> 0
A96: MiniMax H3-Max（海螺） | B96: MiniMax官方 | C96: MiniMax-H3-Max | D96: 480p | E96: 10 | F96: 0 | G96: 每秒 | H96: — | I96: =E96*VLOOKUP("minimax-h3-max|MiniMax官方|480p",费率与参数!$A$16:$G$36,6,0) -> 5 | J96: =MAX(费率与参数!$B$4,CEILING(I96/费率与参数!$B$2,费率与参数!$B$3)) -> 500 | K96: =J96*费率与参数!$B$2 -> 5 | L96: =IF(K96>0,1-I96/K96,0) -> 0
A97: MiniMax H3-Max（海螺） | B97: MiniMax官方 | C97: MiniMax-H3-Max | D97: 480p | E97: 11 | F97: 0 | G97: 每秒 | H97: — | I97: =E97*VLOOKUP("minimax-h3-max|MiniMax官方|480p",费率与参数!$A$16:$G$36,6,0) -> 5.5 | J97: =MAX(费率与参数!$B$4,CEILING(I97/费率与参数!$B$2,费率与参数!$B$3)) -> 550 | K97: =J97*费率与参数!$B$2 -> 5.5 | L97: =IF(K97>0,1-I97/K97,0) -> 0
A98: MiniMax H3-Max（海螺） | B98: MiniMax官方 | C98: MiniMax-H3-Max | D98: 480p | E98: 12 | F98: 0 | G98: 每秒 | H98: — | I98: =E98*VLOOKUP("minimax-h3-max|MiniMax官方|480p",费率与参数!$A$16:$G$36,6,0) -> 6 | J98: =MAX(费率与参数!$B$4,CEILING(I98/费率与参数!$B$2,费率与参数!$B$3)) -> 600 | K98: =J98*费率与参数!$B$2 -> 6 | L98: =IF(K98>0,1-I98/K98,0) -> 0
A99: MiniMax H3-Max（海螺） | B99: MiniMax官方 | C99: MiniMax-H3-Max | D99: 480p | E99: 13 | F99: 0 | G99: 每秒 | H99: — | I99: =E99*VLOOKUP("minimax-h3-max|MiniMax官方|480p",费率与参数!$A$16:$G$36,6,0) -> 6.5 | J99: =MAX(费率与参数!$B$4,CEILING(I99/费率与参数!$B$2,费率与参数!$B$3)) -> 650 | K99: =J99*费率与参数!$B$2 -> 6.5 | L99: =IF(K99>0,1-I99/K99,0) -> 0
A100: MiniMax H3-Max（海螺） | B100: MiniMax官方 | C100: MiniMax-H3-Max | D100: 480p | E100: 14 | F100: 0 | G100: 每秒 | H100: — | I100: =E100*VLOOKUP("minimax-h3-max|MiniMax官方|480p",费率与参数!$A$16:$G$36,6,0) -> 7 | J100: =MAX(费率与参数!$B$4,CEILING(I100/费率与参数!$B$2,费率与参数!$B$3)) -> 700 | K100: =J100*费率与参数!$B$2 -> 7 | L100: =IF(K100>0,1-I100/K100,0) -> 0
A101: MiniMax H3-Max（海螺） | B101: MiniMax官方 | C101: MiniMax-H3-Max | D101: 480p | E101: 15 | F101: 0 | G101: 每秒 | H101: — | I101: =E101*VLOOKUP("minimax-h3-max|MiniMax官方|480p",费率与参数!$A$16:$G$36,6,0) -> 7.5 | J101: =MAX(费率与参数!$B$4,CEILING(I101/费率与参数!$B$2,费率与参数!$B$3)) -> 750 | K101: =J101*费率与参数!$B$2 -> 7.5 | L101: =IF(K101>0,1-I101/K101,0) -> 0
...

Sheet 建议售价清单
A1: 建议售价清单（毛利率按“低参数 50%~100%、高参数 30%~50%”自动插值；H 列可手改单个毛利率，其余自动重算）
A3: 路由 | B3: 渠道 | C3: 模型 | D3: 分辨率 | E3: 时长(秒) | F3: 输入视频秒 | G3: 成本(元) | H3: 目标毛利率 | I3: 建议售价(元) | J3: 建议售价(积分) | K3: 实际毛利率 | L3: 现售价(积分) | M3: 涨幅
A4: Seedance 2.5 | B4: Ark官方 | C4: doubao-seedance-2-5-260628 | D4: 480p | E4: 5 | F4: — | G4: =成本与现售价!$I$4 -> 2.88228 | H4: =MIN(0.95,MAX(费率与参数!$B$6,费率与参数!$B$5-(费率与参数!$B$5-费率与参数!$B$6)*(LN(MAX(G4,0.01))-LN(MIN(成本与现售价!$I$4:$I$172)))/(LN(MAX(成本与现售价!$I$4:$I$172))-LN(MIN(成本与现售价!$I$4:$I$172))))) -> 0.37331728 | I4: =CEILING(G4/(1-H4)/费率与参数!$B$2,费率与参数!$B$3)*费率与参数!$B$2 -> 4.6 | J4: =I4/费率与参数!$B$2 -> 460 | K4: =1-G4/I4 -> 0.37341739 | L4: =成本与现售价!$J$4 -> 289 | M4: =I4/成本与现售价!$K$4-1 -> 0.5916955
A5: Seedance 2.5 | B5: Ark官方 | C5: doubao-seedance-2-5-260628 | D5: 480p | E5: 10 | F5: — | G5: =成本与现售价!$I$5 -> 5.7645 | H5: =MIN(0.95,MAX(费率与参数!$B$6,费率与参数!$B$5-(费率与参数!$B$5-费率与参数!$B$6)*(LN(MAX(G5,0.01))-LN(MIN(成本与现售价!$I$4:$I$172)))/(LN(MAX(成本与现售价!$I$4:$I$172))-LN(MIN(成本与现售价!$I$4:$I$172))))) -> 0.32540238 | I5: =CEILING(G5/(1-H5)/费率与参数!$B$2,费率与参数!$B$3)*费率与参数!$B$2 -> 8.55 | J5: =I5/费率与参数!$B$2 -> 855 | K5: =1-G5/I5 -> 0.32578947 | L5: =成本与现售价!$J$5 -> 577 | M5: =I5/成本与现售价!$K$5-1 -> 0.48180243
A6: Seedance 2.5 | B6: Ark官方 | C6: doubao-seedance-2-5-260628 | D6: 720p | E6: 5 | F6: — | G6: =成本与现售价!$I$6 -> 9.72 | H6: =MIN(0.95,MAX(费率与参数!$B$6,费率与参数!$B$5-(费率与参数!$B$5-费率与参数!$B$6)*(LN(MAX(G6,0.01))-LN(MIN(成本与现售价!$I$4:$I$172)))/(LN(MAX(成本与现售价!$I$4:$I$172))-LN(MIN(成本与现售价!$I$4:$I$172))))) -> 0.28928546 | I6: =CEILING(G6/(1-H6)/费率与参数!$B$2,费率与参数!$B$3)*费率与参数!$B$2 -> 13.68 | J6: =I6/费率与参数!$B$2 -> 1368 | K6: =1-G6/I6 -> 0.28947368 | L6: =成本与现售价!$J$6 -> 972 | M6: =I6/成本与现售价!$K$6-1 -> 0.40740741
A7: Seedance 2.5 | B7: Ark官方 | C7: doubao-seedance-2-5-260628 | D7: 720p | E7: 10 | F7: — | G7: =成本与现售价!$I$7 -> 19.44 | H7: =MIN(0.95,MAX(费率与参数!$B$6,费率与参数!$B$5-(费率与参数!$B$5-费率与参数!$B$6)*(LN(MAX(G7,0.01))-LN(MIN(成本与现售价!$I$4:$I$172)))/(LN(MAX(成本与现售价!$I$4:$I$172))-LN(MIN(成本与现售价!$I$4:$I$172))))) -> 0.24136984 | I7: =CEILING(G7/(1-H7)/费率与参数!$B$2,费率与参数!$B$3)*费率与参数!$B$2 -> 25.63 | J7: =I7/费率与参数!$B$2 -> 2563 | K7: =1-G7/I7 -> 0.24151385 | L7: =成本与现售价!$J$7 -> 1944 | M7: =I7/成本与现售价!$K$7-1 -> 0.31841564
A8: Seedance 2.5 | B8: Ark官方 | C8: doubao-seedance-2-5-260628 | D8: 1080p | E8: 5 | F8: — | G8: =成本与现售价!$I$8 -> 36.45 | H8: =MIN(0.95,MAX(费率与参数!$B$6,费率与参数!$B$5-(费率与参数!$B$5-费率与参数!$B$6)*(LN(MAX(G8,0.01))-LN(MIN(成本与现售价!$I$4:$I$172)))/(LN(MAX(成本与现售价!$I$4:$I$172))-LN(MIN(成本与现售价!$I$4:$I$172))))) -> 0.19791562 | I8: =CEILING(G8/(1-H8)/费率与参数!$B$2,费率与参数!$B$3)*费率与参数!$B$2 -> 45.45 | J8: =I8/费率与参数!$B$2 -> 4545 | K8: =1-G8/I8 -> 0.1980198 | L8: =成本与现售价!$J$8 -> 3645 | M8: =I8/成本与现售价!$K$8-1 -> 0.24691358
A9: Seedance 2.5 | B9: Ark官方 | C9: doubao-seedance-2-5-260628 | D9: 1080p | E9: 10 | F9: — | G9: =成本与现售价!$I$9 -> 72.9 | H9: =MIN(0.95,MAX(费率与参数!$B$6,费率与参数!$B$5-(费率与参数!$B$5-费率与参数!$B$6)*(LN(MAX(G9,0.01))-LN(MIN(成本与现售价!$I$4:$I$172)))/(LN(MAX(成本与现售价!$I$4:$I$172))-LN(MIN(成本与现售价!$I$4:$I$172))))) -> 0.15 | I9: =CEILING(G9/(1-H9)/费率与参数!$B$2,费率与参数!$B$3)*费率与参数!$B$2 -> 85.77 | J9: =I9/费率与参数!$B$2 -> 8577 | K9: =1-G9/I9 -> 0.15005247 | L9: =成本与现售价!$J$9 -> 7290 | M9: =I9/成本与现售价!$K$9-1 -> 0.17654321
A10: Seedance 2.5 | B10: GASIC中转 | C10: doubao-seedance-2-5-260628 | D10: 480p | E10: 4 | F10: — | G10: =成本与现售价!$I$10 -> 2 | H10: =MIN(0.95,MAX(费率与参数!$B$6,费率与参数!$B$5-(费率与参数!$B$5-费率与参数!$B$6)*(LN(MAX(G10,0.01))-LN(MIN(成本与现售价!$I$4:$I$172)))/(LN(MAX(成本与现售价!$I$4:$I$172))-LN(MIN(成本与现售价!$I$4:$I$172))))) -> 0.39857889 | I10: =CEILING(G10/(1-H10)/费率与参数!$B$2,费率与参数!$B$3)*费率与参数!$B$2 -> 3.33 | J10: =I10/费率与参数!$B$2 -> 333 | K10: =1-G10/I10 -> 0.3993994 | L10: =成本与现售价!$J$10 -> 200 | M10: =I10/成本与现售价!$K$10-1 -> 0.665
A11: Seedance 2.5 | B11: GASIC中转 | C11: doubao-seedance-2-5-260628 | D11: 480p | E11: 10 | F11: — | G11: =成本与现售价!$I$11 -> 2 | H11: =MIN(0.95,MAX(费率与参数!$B$6,费率与参数!$B$5-(费率与参数!$B$5-费率与参数!$B$6)*(LN(MAX(G11,0.01))-LN(MIN(成本与现售价!$I$4:$I$172)))/(LN(MAX(成本与现售价!$I$4:$I$172))-LN(MIN(成本与现售价!$I$4:$I$172))))) -> 0.39857889 | I11: =CEILING(G11/(1-H11)/费率与参数!$B$2,费率与参数!$B$3)*费率与参数!$B$2 -> 3.33 | J11: =I11/费率与参数!$B$2 -> 333 | K11: =1-G11/I11 -> 0.3993994 | L11: =成本与现售价!$J$11 -> 200 | M11: =I11/成本与现售价!$K$11-1 -> 0.665
A12: Seedance 2.5 | B12: GASIC中转 | C12: doubao-seedance-2-5-260628 | D12: 480p | E12: 20 | F12: — | G12: =成本与现售价!$I$12 -> 2 | H12: =MIN(0.95,MAX(费率与参数!$B$6,费率与参数!$B$5-(费率与参数!$B$5-费率与参数!$B$6)*(LN(MAX(G12,0.01))-LN(MIN(成本与现售价!$I$4:$I$172)))/(LN(MAX(成本与现售价!$I$4:$I$172))-LN(MIN(成本与现售价!$I$4:$I$172))))) -> 0.39857889 | I12: =CEILING(G12/(1-H12)/费率与参数!$B$2,费率与参数!$B$3)*费率与参数!$B$2 -> 3.33 | J12: =I12/费率与参数!$B$2 -> 333 | K12: =1-G12/I12 -> 0.3993994 | L12: =成本与现售价!$J$12 -> 200 | M12: =I12/成本与现售价!$K$12-1 -> 0.665
A13: Seedance 2.5 | B13: GASIC中转 | C13: doubao-seedance-2-5-260628 | D13: 720p | E13: 4 | F13: — | G13: =成本与现售价!$I$13 -> 2 | H13: =MIN(0.95,MAX(费率与参数!$B$6,费率与参数!$B$5-(费率与参数!$B$5-费率与参数!$B$6)*(LN(MAX(G13,0.01))-LN(MIN(成本与现售价!$I$4:$I$172)))/(LN(MAX(成本与现售价!$I$4:$I$172))-LN(MIN(成本与现售价!$I$4:$I$172))))) -> 0.39857889 | I13: =CEILING(G13/(1-H13)/费率与参数!$B$2,费率与参数!$B$3)*费率与参数!$B$2 -> 3.33 | J13: =I13/费率与参数!$B$2 -> 333 | K13: =1-G13/I13 -> 0.3993994 | L13: =成本与现售价!$J$13 -> 200 | M13: =I13/成本与现售价!$K$13-1 -> 0.665
A14: Seedance 2.5 | B14: GASIC中转 | C14: doubao-seedance-2-5-260628 | D14: 720p | E14: 10 | F14: — | G14: =成本与现售价!$I$14 -> 2 | H14: =MIN(0.95,MAX(费率与参数!$B$6,费率与参数!$B$5-(费率与参数!$B$5-费率与参数!$B$6)*(LN(MAX(G14,0.01))-LN(MIN(成本与现售价!$I$4:$I$172)))/(LN(MAX(成本与现售价!$I$4:$I$172))-LN(MIN(成本与现售价!$I$4:$I$172))))) -> 0.39857889 | I14: =CEILING(G14/(1-H14)/费率与参数!$B$2,费率与参数!$B$3)*费率与参数!$B$2 -> 3.33 | J14: =I14/费率与参数!$B$2 -> 333 | K14: =1-G14/I14 -> 0.3993994 | L14: =成本与现售价!$J$14 -> 200 | M14: =I14/成本与现售价!$K$14-1 -> 0.665
A15: Seedance 2.5 | B15: GASIC中转 | C15: doubao-seedance-2-5-260628 | D15: 720p | E15: 20 | F15: — | G15: =成本与现售价!$I$15 -> 2 | H15: =MIN(0.95,MAX(费率与参数!$B$6,费率与参数!$B$5-(费率与参数!$B$5-费率与参数!$B$6)*(LN(MAX(G15,0.01))-LN(MIN(成本与现售价!$I$4:$I$172)))/(LN(MAX(成本与现售价!$I$4:$I$172))-LN(MIN(成本与现售价!$I$4:$I$172))))) -> 0.39857889 | I15: =CEILING(G15/(1-H15)/费率与参数!$B$2,费率与参数!$B$3)*费率与参数!$B$2 -> 3.33 | J15: =I15/费率与参数!$B$2 -> 333 | K15: =1-G15/I15 -> 0.3993994 | L15: =成本与现售价!$J$15 -> 200 | M15: =I15/成本与现售价!$K$15-1 -> 0.665
A16: Seedance 2.5 | B16: GASIC中转 | C16: doubao-seedance-2-5-260628 | D16: 1080p | E16: 4 | F16: — | G16: =成本与现售价!$I$16 -> 2 | H16: =MIN(0.95,MAX(费率与参数!$B$6,费率与参数!$B$5-(费率与参数!$B$5-费率与参数!$B$6)*(LN(MAX(G16,0.01))-LN(MIN(成本与现售价!$I$4:$I$172)))/(LN(MAX(成本与现售价!$I$4:$I$172))-LN(MIN(成本与现售价!$I$4:$I$172))))) -> 0.39857889 | I16: =CEILING(G16/(1-H16)/费率与参数!$B$2,费率与参数!$B$3)*费率与参数!$B$2 -> 3.33 | J16: =I16/费率与参数!$B$2 -> 333 | K16: =1-G16/I16 -> 0.3993994 | L16: =成本与现售价!$J$16 -> 200 | M16: =I16/成本与现售价!$K$16-1 -> 0.665
A17: Seedance 2.5 | B17: GASIC中转 | C17: doubao-seedance-2-5-260628 | D17: 1080p | E17: 10 | F17: — | G17: =成本与现售价!$I$17 -> 2 | H17: =MIN(0.95,MAX(费率与参数!$B$6,费率与参数!$B$5-(费率与参数!$B$5-费率与参数!$B$6)*(LN(MAX(G17,0.01))-LN(MIN(成本与现售价!$I$4:$I$172)))/(LN(MAX(成本与现售价!$I$4:$I$172))-LN(MIN(成本与现售价!$I$4:$I$172))))) -> 0.39857889 | I17: =CEILING(G17/(1-H17)/费率与参数!$B$2,费率与参数!$B$3)*费率与参数!$B$2 -> 3.33 | J17: =I17/费率与参数!$B$2 -> 333 | K17: =1-G17/I17 -> 0.3993994 | L17: =成本与现售价!$J$17 -> 200 | M17: =I17/成本与现售价!$K$17-1 -> 0.665
A18: Seedance 2.5 | B18: GASIC中转 | C18: doubao-seedance-2-5-260628 | D18: 1080p | E18: 20 | F18: — | G18: =成本与现售价!$I$18 -> 2 | H18: =MIN(0.95,MAX(费率与参数!$B$6,费率与参数!$B$5-(费率与参数!$B$5-费率与参数!$B$6)*(LN(MAX(G18,0.01))-LN(MIN(成本与现售价!$I$4:$I$172)))/(LN(MAX(成本与现售价!$I$4:$I$172))-LN(MIN(成本与现售价!$I$4:$I$172))))) -> 0.39857889 | I18: =CEILING(G18/(1-H18)/费率与参数!$B$2,费率与参数!$B$3)*费率与参数!$B$2 -> 3.33 | J18: =I18/费率与参数!$B$2 -> 333 | K18: =1-G18/I18 -> 0.3993994 | L18: =成本与现售价!$J$18 -> 200 | M18: =I18/成本与现售价!$K$18-1 -> 0.665
A19: Seedance 2.0 | B19: Ark官方 | C19: doubao-seedance-2-0-260128 | D19: 480p | E19: 5 | F19: — | G19: =成本与现售价!$I$19 -> 1.44114 | H19: =MIN(0.95,MAX(费率与参数!$B$6,费率与参数!$B$5-(费率与参数!$B$5-费率与参数!$B$6)*(LN(MAX(G19,0.01))-LN(MIN(成本与现售价!$I$4:$I$172)))/(LN(MAX(成本与现售价!$I$4:$I$172))-LN(MIN(成本与现售价!$I$4:$I$172))))) -> 0.42123289 | I19: =CEILING(G19/(1-H19)/费率与参数!$B$2,费率与参数!$B$3)*费率与参数!$B$2 -> 2.5 | J19: =I19/费率与参数!$B$2 -> 250 | K19: =1-G19/I19 -> 0.423544 | L19: =成本与现售价!$J$19 -> 145 | M19: =I19/成本与现售价!$K$19-1 -> 0.72413793
A20: Seedance 2.0 | B20: Ark官方 | C20: doubao-seedance-2-0-260128 | D20: 480p | E20: 10 | F20: — | G20: =成本与现售价!$I$20 -> 2.88225 | H20: =MIN(0.95,MAX(费率与参数!$B$6,费率与参数!$B$5-(费率与参数!$B$5-费率与参数!$B$6)*(LN(MAX(G20,0.01))-LN(MIN(成本与现售价!$I$4:$I$172)))/(LN(MAX(成本与现售价!$I$4:$I$172))-LN(MIN(成本与现售价!$I$4:$I$172))))) -> 0.373318 | I20: =CEILING(G20/(1-H20)/费率与参数!$B$2,费率与参数!$B$3)*费率与参数!$B$2 -> 4.6 | J20: =I20/费率与参数!$B$2 -> 460 | K20: =1-G20/I20 -> 0.37342391 | L20: =成本与现售价!$J$20 -> 289 | M20: =I20/成本与现售价!$K$20-1 -> 0.5916955
A21: Seedance 2.0 | B21: Ark官方 | C21: doubao-seedance-2-0-260128 | D21: 720p | E21: 5 | F21: — | G21: =成本与现售价!$I$21 -> 4.86 | H21: =MIN(0.95,MAX(费率与参数!$B$6,费率与参数!$B$5-(费率与参数!$B$5-费率与参数!$B$6)*(LN(MAX(G21,0.01))-LN(MIN(成本与现售价!$I$4:$I$172)))/(LN(MAX(成本与现售价!$I$4:$I$172))-LN(MIN(成本与现售价!$I$4:$I$172))))) -> 0.33720108 | I21: =CEILING(G21/(1-H21)/费率与参数!$B$2,费率与参数!$B$3)*费率与参数!$B$2 -> 7.34 | J21: =I21/费率与参数!$B$2 -> 734 | K21: =1-G21/I21 -> 0.33787466 | L21: =成本与现售价!$J$21 -> 486 | M21: =I21/成本与现售价!$K$21-1 -> 0.51028807
A22: Seedance 2.0 | B22: Ark官方 | C22: doubao-seedance-2-0-260128 | D22: 720p | E22: 10 | F22: — | G22: =成本与现售价!$I$22 -> 9.72 | H22: =MIN(0.95,MAX(费率与参数!$B$6,费率与参数!$B$5-(费率与参数!$B$5-费率与参数!$B$6)*(LN(MAX(G22,0.01))-LN(MIN(成本与现售价!$I$4:$I$172)))/(LN(MAX(成本与现售价!$I$4:$I$172))-LN(MIN(成本与现售价!$I$4:$I$172))))) -> 0.28928546 | I22: =CEILING(G22/(1-H22)/费率与参数!$B$2,费率与参数!$B$3)*费率与参数!$B$2 -> 13.68 | J22: =I22/费率与参数!$B$2 -> 1368 | K22: =1-G22/I22 -> 0.28947368 | L22: =成本与现售价!$J$22 -> 972 | M22: =I22/成本与现售价!$K$22-1 -> 0.40740741
A23: Seedance 2.0 | B23: Ark官方 | C23: doubao-seedance-2-0-260128 | D23: 1080p | E23: 5 | F23: — | G23: =成本与现售价!$I$23 -> 18.225 | H23: =MIN(0.95,MAX(费率与参数!$B$6,费率与参数!$B$5-(费率与参数!$B$5-费率与参数!$B$6)*(LN(MAX(G23,0.01))-LN(MIN(成本与现售价!$I$4:$I$172)))/(LN(MAX(成本与现售价!$I$4:$I$172))-LN(MIN(成本与现售价!$I$4:$I$172))))) -> 0.24583124 | I23: =CEILING(G23/(1-H23)/费率与参数!$B$2,费率与参数!$B$3)*费率与参数!$B$2 -> 24.17 | J23: =I23/费率与参数!$B$2 -> 2417 | K23: =1-G23/I23 -> 0.24596607 | L23: =成本与现售价!$J$23 -> 1823 | M23: =I23/成本与现售价!$K$23-1 -> 0.32583653
A24: Seedance 2.0 | B24: Ark官方 | C24: doubao-seedance-2-0-260128 | D24: 1080p | E24: 10 | F24: — | G24: =成本与现售价!$I$24 -> 36.45 | H24: =MIN(0.95,MAX(费率与参数!$B$6,费率与参数!$B$5-(费率与参数!$B$5-费率与参数!$B$6)*(LN(MAX(G24,0.01))-LN(MIN(成本与现售价!$I$4:$I$172)))/(LN(MAX(成本与现售价!$I$4:$I$172))-LN(MIN(成本与现售价!$I$4:$I$172))))) -> 0.19791562 | I24: =CEILING(G24/(1-H24)/费率与参数!$B$2,费率与参数!$B$3)*费率与参数!$B$2 -> 45.45 | J24: =I24/费率与参数!$B$2 -> 4545 | K24: =1-G24/I24 -> 0.1980198 | L24: =成本与现售价!$J$24 -> 3645 | M24: =I24/成本与现售价!$K$24-1 -> 0.24691358
A25: Seedance 2.0 | B25: GASIC中转 | C25: doubao-seedance-2-0-260128 | D25: 480p | E25: 4 | F25: — | G25: =成本与现售价!$I$25 -> 2 | H25: =MIN(0.95,MAX(费率与参数!$B$6,费率与参数!$B$5-(费率与参数!$B$5-费率与参数!$B$6)*(LN(MAX(G25,0.01))-LN(MIN(成本与现售价!$I$4:$I$172)))/(LN(MAX(成本与现售价!$I$4:$I$172))-LN(MIN(成本与现售价!$I$4:$I$172))))) -> 0.39857889 | I25: =CEILING(G25/(1-H25)/费率与参数!$B$2,费率与参数!$B$3)*费率与参数!$B$2 -> 3.33 | J25: =I25/费率与参数!$B$2 -> 333 | K25: =1-G25/I25 -> 0.3993994 | L25: =成本与现售价!$J$25 -> 200 | M25: =I25/成本与现售价!$K$25-1 -> 0.665
A26: Seedance 2.0 | B26: GASIC中转 | C26: doubao-seedance-2-0-260128 | D26: 480p | E26: 15 | F26: — | G26: =成本与现售价!$I$26 -> 2 | H26: =MIN(0.95,MAX(费率与参数!$B$6,费率与参数!$B$5-(费率与参数!$B$5-费率与参数!$B$6)*(LN(MAX(G26,0.01))-LN(MIN(成本与现售价!$I$4:$I$172)))/(LN(MAX(成本与现售价!$I$4:$I$172))-LN(MIN(成本与现售价!$I$4:$I$172))))) -> 0.39857889 | I26: =CEILING(G26/(1-H26)/费率与参数!$B$2,费率与参数!$B$3)*费率与参数!$B$2 -> 3.33 | J26: =I26/费率与参数!$B$2 -> 333 | K26: =1-G26/I26 -> 0.3993994 | L26: =成本与现售价!$J$26 -> 200 | M26: =I26/成本与现售价!$K$26-1 -> 0.665
A27: Seedance 2.0 | B27: GASIC中转 | C27: doubao-seedance-2-0-260128 | D27: 720p | E27: 4 | F27: — | G27: =成本与现售价!$I$27 -> 2 | H27: =MIN(0.95,MAX(费率与参数!$B$6,费率与参数!$B$5-(费率与参数!$B$5-费率与参数!$B$6)*(LN(MAX(G27,0.01))-LN(MIN(成本与现售价!$I$4:$I$172)))/(LN(MAX(成本与现售价!$I$4:$I$172))-LN(MIN(成本与现售价!$I$4:$I$172))))) -> 0.39857889 | I27: =CEILING(G27/(1-H27)/费率与参数!$B$2,费率与参数!$B$3)*费率与参数!$B$2 -> 3.33 | J27: =I27/费率与参数!$B$2 -> 333 | K27: =1-G27/I27 -> 0.3993994 | L27: =成本与现售价!$J$27 -> 200 | M27: =I27/成本与现售价!$K$27-1 -> 0.665
A28: Seedance 2.0 | B28: GASIC中转 | C28: doubao-seedance-2-0-260128 | D28: 720p | E28: 15 | F28: — | G28: =成本与现售价!$I$28 -> 2 | H28: =MIN(0.95,MAX(费率与参数!$B$6,费率与参数!$B$5-(费率与参数!$B$5-费率与参数!$B$6)*(LN(MAX(G28,0.01))-LN(MIN(成本与现售价!$I$4:$I$172)))/(LN(MAX(成本与现售价!$I$4:$I$172))-LN(MIN(成本与现售价!$I$4:$I$172))))) -> 0.39857889 | I28: =CEILING(G28/(1-H28)/费率与参数!$B$2,费率与参数!$B$3)*费率与参数!$B$2 -> 3.33 | J28: =I28/费率与参数!$B$2 -> 333 | K28: =1-G28/I28 -> 0.3993994 | L28: =成本与现售价!$J$28 -> 200 | M28: =I28/成本与现售价!$K$28-1 -> 0.665
A29: Seedance 2.0 | B29: GASIC中转 | C29: doubao-seedance-2-0-260128 | D29: 1080p | E29: 4 | F29: — | G29: =成本与现售价!$I$29 -> 2 | H29: =MIN(0.95,MAX(费率与参数!$B$6,费率与参数!$B$5-(费率与参数!$B$5-费率与参数!$B$6)*(LN(MAX(G29,0.01))-LN(MIN(成本与现售价!$I$4:$I$172)))/(LN(MAX(成本与现售价!$I$4:$I$172))-LN(MIN(成本与现售价!$I$4:$I$172))))) -> 0.39857889 | I29: =CEILING(G29/(1-H29)/费率与参数!$B$2,费率与参数!$B$3)*费率与参数!$B$2 -> 3.33 | J29: =I29/费率与参数!$B$2 -> 333 | K29: =1-G29/I29 -> 0.3993994 | L29: =成本与现售价!$J$29 -> 200 | M29: =I29/成本与现售价!$K$29-1 -> 0.665
A30: Seedance 2.0 | B30: GASIC中转 | C30: doubao-seedance-2-0-260128 | D30: 1080p | E30: 15 | F30: — | G30: =成本与现售价!$I$30 -> 2 | H30: =MIN(0.95,MAX(费率与参数!$B$6,费率与参数!$B$5-(费率与参数!$B$5-费率与参数!$B$6)*(LN(MAX(G30,0.01))-LN(MIN(成本与现售价!$I$4:$I$172)))/(LN(MAX(成本与现售价!$I$4:$I$172))-LN(MIN(成本与现售价!$I$4:$I$172))))) -> 0.39857889 | I30: =CEILING(G30/(1-H30)/费率与参数!$B$2,费率与参数!$B$3)*费率与参数!$B$2 -> 3.33 | J30: =I30/费率与参数!$B$2 -> 333 | K30: =1-G30/I30 -> 0.3993994 | L30: =成本与现售价!$J$30 -> 200 | M30: =I30/成本与现售价!$K$30-1 -> 0.665
A31: Seedance 2.0 Mini（极速版） | B31: Ark官方 | C31: doubao-seedance-2-0-mini-260615 | D31: 480p | E31: 4 | F31: — | G31: =成本与现售价!$I$31 -> 0.46116 | H31: =MIN(0.95,MAX(费率与参数!$B$6,费率与参数!$B$5-(费率与参数!$B$5-费率与参数!$B$6)*(LN(MAX(G31,0.01))-LN(MIN(成本与现售价!$I$4:$I$172)))/(LN(MAX(成本与现售价!$I$4:$I$172))-LN(MIN(成本与现售价!$I$4:$I$172))))) -> 0.5 | I31: =CEILING(G31/(1-H31)/费率与参数!$B$2,费率与参数!$B$3)*费率与参数!$B$2 -> 0.93 | J31: =I31/费率与参数!$B$2 -> 93 | K31: =1-G31/I31 -> 0.50412903 | L31: =成本与现售价!$J$31 -> 47 | M31: =I31/成本与现售价!$K$31-1 -> 0.9787234
A32: Seedance 2.0 Mini（极速版） | B32: Ark官方 | C32: doubao-seedance-2-0-mini-260615 | D32: 480p | E32: 5 | F32: — | G32: =成本与现售价!$I$32 -> 0.576456 | H32: =MIN(0.95,MAX(费率与参数!$B$6,费率与参数!$B$5-(费率与参数!$B$5-费率与参数!$B$6)*(LN(MAX(G32,0.01))-LN(MIN(成本与现售价!$I$4:$I$172)))/(LN(MAX(成本与现售价!$I$4:$I$172))-LN(MIN(成本与现售价!$I$4:$I$172))))) -> 0.4845739 | I32: =CEILING(G32/(1-H32)/费率与参数!$B$2,费率与参数!$B$3)*费率与参数!$B$2 -> 1.12 | J32: =I32/费率与参数!$B$2 -> 112 | K32: =1-G32/I32 -> 0.48530714 | L32: =成本与现售价!$J$32 -> 58 | M32: =I32/成本与现售价!$K$32-1 -> 0.93103448
A33: Seedance 2.0 Mini（极速版） | B33: Ark官方 | C33: doubao-seedance-2-0-mini-260615 | D33: 480p | E33: 6 | F33: — | G33: =成本与现售价!$I$33 -> 0.69174 | H33: =MIN(0.95,MAX(费率与参数!$B$6,费率与参数!$B$5-(费率与参数!$B$5-费率与参数!$B$6)*(LN(MAX(G33,0.01))-LN(MIN(成本与现售价!$I$4:$I$172)))/(LN(MAX(成本与现售价!$I$4:$I$172))-LN(MIN(成本与现售价!$I$4:$I$172))))) -> 0.47197116 | I33: =CEILING(G33/(1-H33)/费率与参数!$B$2,费率与参数!$B$3)*费率与参数!$B$2 -> 1.32 | J33: =I33/费率与参数!$B$2 -> 132 | K33: =1-G33/I33 -> 0.47595455 | L33: =成本与现售价!$J$33 -> 70 | M33: =I33/成本与现售价!$K$33-1 -> 0.88571429
A34: Seedance 2.0 Mini（极速版） | B34: Ark官方 | C34: doubao-seedance-2-0-mini-260615 | D34: 480p | E34: 7 | F34: — | G34: =成本与现售价!$I$34 -> 0.807036 | H34: =MIN(0.95,MAX(费率与参数!$B$6,费率与参数!$B$5-(费率与参数!$B$5-费率与参数!$B$6)*(LN(MAX(G34,0.01))-LN(MIN(成本与现售价!$I$4:$I$172)))/(LN(MAX(成本与现售价!$I$4:$I$172))-LN(MIN(成本与现售价!$I$4:$I$172))))) -> 0.46131458 | I34: =CEILING(G34/(1-H34)/费率与参数!$B$2,费率与参数!$B$3)*费率与参数!$B$2 -> 1.5 | J34: =I34/费率与参数!$B$2 -> 150 | K34: =1-G34/I34 -> 0.461976 | L34: =成本与现售价!$J$34 -> 81 | M34: =I34/成本与现售价!$K$34-1 -> 0.85185185
A35: Seedance 2.0 Mini（极速版） | B35: Ark官方 | C35: doubao-seedance-2-0-mini-260615 | D35: 480p | E35: 8 | F35: — | G35: =成本与现售价!$I$35 -> 0.92232 | H35: =MIN(0.95,MAX(费率与参数!$B$6,费率与参数!$B$5-(费率与参数!$B$5-费率与参数!$B$6)*(LN(MAX(G35,0.01))-LN(MIN(成本与现售价!$I$4:$I$172)))/(LN(MAX(成本与现售价!$I$4:$I$172))-LN(MIN(成本与现售价!$I$4:$I$172))))) -> 0.45208438 | I35: =CEILING(G35/(1-H35)/费率与参数!$B$2,费率与参数!$B$3)*费率与参数!$B$2 -> 1.69 | J35: =I35/费率与参数!$B$2 -> 169 | K35: =1-G35/I35 -> 0.45424852 | L35: =成本与现售价!$J$35 -> 93 | M35: =I35/成本与现售价!$K$35-1 -> 0.8172043
A36: Seedance 2.0 Mini（极速版） | B36: Ark官方 | C36: doubao-seedance-2-0-mini-260615 | D36: 480p | E36: 9 | F36: — | G36: =成本与现售价!$I$36 -> 1.037616 | H36: =MIN(0.95,MAX(费率与参数!$B$6,费率与参数!$B$5-(费率与参数!$B$5-费率与参数!$B$6)*(LN(MAX(G36,0.01))-LN(MIN(成本与现售价!$I$4:$I$172)))/(LN(MAX(成本与现售价!$I$4:$I$172))-LN(MIN(成本与现售价!$I$4:$I$172))))) -> 0.44394192 | I36: =CEILING(G36/(1-H36)/费率与参数!$B$2,费率与参数!$B$3)*费率与参数!$B$2 -> 1.87 | J36: =I36/费率与参数!$B$2 -> 187 | K36: =1-G36/I36 -> 0.44512513 | L36: =成本与现售价!$J$36 -> 104 | M36: =I36/成本与现售价!$K$36-1 -> 0.79807692
A37: Seedance 2.0 Mini（极速版） | B37: Ark官方 | C37: doubao-seedance-2-0-mini-260615 | D37: 480p | E37: 10 | F37: — | G37: =成本与现售价!$I$37 -> 1.1529 | H37: =MIN(0.95,MAX(费率与参数!$B$6,费率与参数!$B$5-(费率与参数!$B$5-费率与参数!$B$6)*(LN(MAX(G37,0.01))-LN(MIN(成本与现售价!$I$4:$I$172)))/(LN(MAX(成本与现售价!$I$4:$I$172))-LN(MIN(成本与现售价!$I$4:$I$172))))) -> 0.436659 | I37: =CEILING(G37/(1-H37)/费率与参数!$B$2,费率与参数!$B$3)*费率与参数!$B$2 -> 2.05 | J37: =I37/费率与参数!$B$2 -> 205 | K37: =1-G37/I37 -> 0.43760976 | L37: =成本与现售价!$J$37 -> 116 | M37: =I37/成本与现售价!$K$37-1 -> 0.76724138
A38: Seedance 2.0 Mini（极速版） | B38: Ark官方 | C38: doubao-seedance-2-0-mini-260615 | D38: 480p | E38: 11 | F38: — | G38: =成本与现售价!$I$38 -> 1.268196 | H38: =MIN(0.95,MAX(费率与参数!$B$6,费率与参数!$B$5-(费率与参数!$B$5-费率与参数!$B$6)*(LN(MAX(G38,0.01))-LN(MIN(成本与现售价!$I$4:$I$172)))/(LN(MAX(成本与现售价!$I$4:$I$172))-LN(MIN(成本与现售价!$I$4:$I$172))))) -> 0.4300701 | I38: =CEILING(G38/(1-H38)/费率与参数!$B$2,费率与参数!$B$3)*费率与参数!$B$2 -> 2.23 | J38: =I38/费率与参数!$B$2 -> 223 | K38: =1-G38/I38 -> 0.43130224 | L38: =成本与现售价!$J$38 -> 127 | M38: =I38/成本与现售价!$K$38-1 -> 0.75590551
A39: Seedance 2.0 Mini（极速版） | B39: Ark官方 | C39: doubao-seedance-2-0-mini-260615 | D39: 480p | E39: 12 | F39: — | G39: =成本与现售价!$I$39 -> 1.38348 | H39: =MIN(0.95,MAX(费率与参数!$B$6,费率与参数!$B$5-(费率与参数!$B$5-费率与参数!$B$6)*(LN(MAX(G39,0.01))-LN(MIN(成本与现售价!$I$4:$I$172)))/(LN(MAX(成本与现售价!$I$4:$I$172))-LN(MIN(成本与现售价!$I$4:$I$172))))) -> 0.42405554 | I39: =CEILING(G39/(1-H39)/费率与参数!$B$2,费率与参数!$B$3)*费率与参数!$B$2 -> 2.41 | J39: =I39/费率与参数!$B$2 -> 241 | K39: =1-G39/I39 -> 0.42594191 | L39: =成本与现售价!$J$39 -> 139 | M39: =I39/成本与现售价!$K$39-1 -> 0.73381295
A40: Seedance 2.0 Mini（极速版） | B40: Ark官方 | C40: doubao-seedance-2-0-mini-260615 | D40: 480p | E40: 13 | F40: — | G40: =成本与现售价!$I$40 -> 1.498776 | H40: =MIN(0.95,MAX(费率与参数!$B$6,费率与参数!$B$5-(费率与参数!$B$5-费率与参数!$B$6)*(LN(MAX(G40,0.01))-LN(MIN(成本与现售价!$I$4:$I$172)))/(LN(MAX(成本与现售价!$I$4:$I$172))-LN(MIN(成本与现售价!$I$4:$I$172))))) -> 0.4185221 | I40: =CEILING(G40/(1-H40)/费率与参数!$B$2,费率与参数!$B$3)*费率与参数!$B$2 -> 2.58 | J40: =I40/费率与参数!$B$2 -> 258 | K40: =1-G40/I40 -> 0.41907907 | L40: =成本与现售价!$J$40 -> 150 | M40: =I40/成本与现售价!$K$40-1 -> 0.72
A41: Seedance 2.0 Mini（极速版） | B41: Ark官方 | C41: doubao-seedance-2-0-mini-260615 | D41: 480p | E41: 14 | F41: — | G41: =成本与现售价!$I$41 -> 1.61406 | H41: =MIN(0.95,MAX(费率与参数!$B$6,费率与参数!$B$5-(费率与参数!$B$5-费率与参数!$B$6)*(LN(MAX(G41,0.01))-LN(MIN(成本与现售价!$I$4:$I$172)))/(LN(MAX(成本与现售价!$I$4:$I$172))-LN(MIN(成本与现售价!$I$4:$I$172))))) -> 0.41339947 | I41: =CEILING(G41/(1-H41)/费率与参数!$B$2,费率与参数!$B$3)*费率与参数!$B$2 -> 2.76 | J41: =I41/费率与参数!$B$2 -> 276 | K41: =1-G41/I41 -> 0.41519565 | L41: =成本与现售价!$J$41 -> 162 | M41: =I41/成本与现售价!$K$41-1 -> 0.7037037
A42: Seedance 2.0 Mini（极速版） | B42: Ark官方 | C42: doubao-seedance-2-0-mini-260615 | D42: 480p | E42: 15 | F42: — | G42: =成本与现售价!$I$42 -> 1.729356 | H42: =MIN(0.95,MAX(费率与参数!$B$6,费率与参数!$B$5-(费率与参数!$B$5-费率与参数!$B$6)*(LN(MAX(G42,0.01))-LN(MIN(成本与现售价!$I$4:$I$172)))/(LN(MAX(成本与现售价!$I$4:$I$172))-LN(MIN(成本与现售价!$I$4:$I$172))))) -> 0.40862992 | I42: =CEILING(G42/(1-H42)/费率与参数!$B$2,费率与参数!$B$3)*费率与参数!$B$2 -> 2.93 | J42: =I42/费率与参数!$B$2 -> 293 | K42: =1-G42/I42 -> 0.40977611 | L42: =成本与现售价!$J$42 -> 173 | M42: =I42/成本与现售价!$K$42-1 -> 0.69364162
A43: Seedance 2.0 Mini（极速版） | B43: Ark官方 | C43: doubao-seedance-2-0-mini-260615 | D43: 720p | E43: 4 | F43: — | G43: =成本与现售价!$I$43 -> 1.5552 | H43: =MIN(0.95,MAX(费率与参数!$B$6,费率与参数!$B$5-(费率与参数!$B$5-费率与参数!$B$6)*(LN(MAX(G43,0.01))-LN(MIN(成本与现售价!$I$4:$I$172)))/(LN(MAX(成本与现售价!$I$4:$I$172))-LN(MIN(成本与现售价!$I$4:$I$172))))) -> 0.41596746 | I43: =CEILING(G43/(1-H43)/费率与参数!$B$2,费率与参数!$B$3)*费率与参数!$B$2 -> 2.67 | J43: =I43/费率与参数!$B$2 -> 267 | K43: =1-G43/I43 -> 0.41752809 | L43: =成本与现售价!$J$43 -> 156 | M43: =I43/成本与现售价!$K$43-1 -> 0.71153846
A44: Seedance 2.0 Mini（极速版） | B44: Ark官方 | C44: doubao-seedance-2-0-mini-260615 | D44: 720p | E44: 5 | F44: — | G44: =成本与现售价!$I$44 -> 1.944 | H44: =MIN(0.95,MAX(费率与参数!$B$6,费率与参数!$B$5-(费率与参数!$B$5-费率与参数!$B$6)*(LN(MAX(G44,0.01))-LN(MIN(成本与现售价!$I$4:$I$172)))/(LN(MAX(成本与现售价!$I$4:$I$172))-LN(MIN(成本与现售价!$I$4:$I$172))))) -> 0.40054208 | I44: =CEILING(G44/(1-H44)/费率与参数!$B$2,费率与参数!$B$3)*费率与参数!$B$2 -> 3.25 | J44: =I44/费率与参数!$B$2 -> 325 | K44: =1-G44/I44 -> 0.40184615 | L44: =成本与现售价!$J$44 -> 195 | M44: =I44/成本与现售价!$K$44-1 -> 0.66666667
A45: Seedance 2.0 Mini（极速版） | B45: Ark官方 | C45: doubao-seedance-2-0-mini-260615 | D45: 720p | E45: 6 | F45: — | G45: =成本与现售价!$I$45 -> 2.3328 | H45: =MIN(0.95,MAX(费率与参数!$B$6,费率与参数!$B$5-(费率与参数!$B$5-费率与参数!$B$6)*(LN(MAX(G45,0.01))-LN(MIN(成本与现售价!$I$4:$I$172)))/(LN(MAX(成本与现售价!$I$4:$I$172))-LN(MIN(成本与现售价!$I$4:$I$172))))) -> 0.38793862 | I45: =CEILING(G45/(1-H45)/费率与参数!$B$2,费率与参数!$B$3)*费率与参数!$B$2 -> 3.82 | J45: =I45/费率与参数!$B$2 -> 382 | K45: =1-G45/I45 -> 0.38931937 | L45: =成本与现售价!$J$45 -> 234 | M45: =I45/成本与现售价!$K$45-1 -> 0.63247863
A46: Seedance 2.0 Mini（极速版） | B46: Ark官方 | C46: doubao-seedance-2-0-mini-260615 | D46: 720p | E46: 7 | F46: — | G46: =成本与现售价!$I$46 -> 2.7216 | H46: =MIN(0.95,MAX(费率与参数!$B$6,费率与参数!$B$5-(费率与参数!$B$5-费率与参数!$B$6)*(LN(MAX(G46,0.01))-LN(MIN(成本与现售价!$I$4:$I$172)))/(LN(MAX(成本与现售价!$I$4:$I$172))-LN(MIN(成本与现售价!$I$4:$I$172))))) -> 0.37728255 | I46: =CEILING(G46/(1-H46)/费率与参数!$B$2,费率与参数!$B$3)*费率与参数!$B$2 -> 4.38 | J46: =I46/费率与参数!$B$2 -> 438 | K46: =1-G46/I46 -> 0.37863014 | L46: =成本与现售价!$J$46 -> 273 | M46: =I46/成本与现售价!$K$46-1 -> 0.6043956
A47: Seedance 2.0 Mini（极速版） | B47: Ark官方 | C47: doubao-seedance-2-0-mini-260615 | D47: 720p | E47: 8 | F47: — | G47: =成本与现售价!$I$47 -> 3.1104 | H47: =MIN(0.95,MAX(费率与参数!$B$6,费率与参数!$B$5-(费率与参数!$B$5-费率与参数!$B$6)*(LN(MAX(G47,0.01))-LN(MIN(成本与现售价!$I$4:$I$172)))/(LN(MAX(成本与现售价!$I$4:$I$172))-LN(MIN(成本与现售价!$I$4:$I$172))))) -> 0.36805185 | I47: =CEILING(G47/(1-H47)/费率与参数!$B$2,费率与参数!$B$3)*费率与参数!$B$2 -> 4.93 | J47: =I47/费率与参数!$B$2 -> 493 | K47: =1-G47/I47 -> 0.36908722 | L47: =成本与现售价!$J$47 -> 312 | M47: =I47/成本与现售价!$K$47-1 -> 0.58012821
A48: Seedance 2.0 Mini（极速版） | B48: Ark官方 | C48: doubao-seedance-2-0-mini-260615 | D48: 720p | E48: 9 | F48: — | G48: =成本与现售价!$I$48 -> 3.4992 | H48: =MIN(0.95,MAX(费率与参数!$B$6,费率与参数!$B$5-(费率与参数!$B$5-费率与参数!$B$6)*(LN(MAX(G48,0.01))-LN(MIN(成本与现售价!$I$4:$I$172)))/(LN(MAX(成本与现售价!$I$4:$I$172))-LN(MIN(成本与现售价!$I$4:$I$172))))) -> 0.35990978 | I48: =CEILING(G48/(1-H48)/费率与参数!$B$2,费率与参数!$B$3)*费率与参数!$B$2 -> 5.47 | J48: =I48/费率与参数!$B$2 -> 547 | K48: =1-G48/I48 -> 0.3602925 | L48: =成本与现售价!$J$48 -> 350 | M48: =I48/成本与现售价!$K$48-1 -> 0.56285714
A49: Seedance 2.0 Mini（极速版） | B49: Ark官方 | C49: doubao-seedance-2-0-mini-260615 | D49: 720p | E49: 10 | F49: — | G49: =成本与现售价!$I$49 -> 3.888 | H49: =MIN(0.95,MAX(费率与参数!$B$6,费率与参数!$B$5-(费率与参数!$B$5-费率与参数!$B$6)*(LN(MAX(G49,0.01))-LN(MIN(成本与现售价!$I$4:$I$172)))/(LN(MAX(成本与现售价!$I$4:$I$172))-LN(MIN(成本与现售价!$I$4:$I$172))))) -> 0.35262646 | I49: =CEILING(G49/(1-H49)/费率与参数!$B$2,费率与参数!$B$3)*费率与参数!$B$2 -> 6.01 | J49: =I49/费率与参数!$B$2 -> 601 | K49: =1-G49/I49 -> 0.3530782 | L49: =成本与现售价!$J$49 -> 389 | M49: =I49/成本与现售价!$K$49-1 -> 0.54498715
A50: Seedance 2.0 Mini（极速版） | B50: Ark官方 | C50: doubao-seedance-2-0-mini-260615 | D50: 720p | E50: 11 | F50: — | G50: =成本与现售价!$I$50 -> 4.2768 | H50: =MIN(0.95,MAX(费率与参数!$B$6,费率与参数!$B$5-(费率与参数!$B$5-费率与参数!$B$6)*(LN(MAX(G50,0.01))-LN(MIN(成本与现售价!$I$4:$I$172)))/(LN(MAX(成本与现售价!$I$4:$I$172))-LN(MIN(成本与现售价!$I$4:$I$172))))) -> 0.3460379 | I50: =CEILING(G50/(1-H50)/费率与参数!$B$2,费率与参数!$B$3)*费率与参数!$B$2 -> 6.54 | J50: =I50/费率与参数!$B$2 -> 654 | K50: =1-G50/I50 -> 0.34605505 | L50: =成本与现售价!$J$50 -> 428 | M50: =I50/成本与现售价!$K$50-1 -> 0.52803738
A51: Seedance 2.0 Mini（极速版） | B51: Ark官方 | C51: doubao-seedance-2-0-mini-260615 | D51: 720p | E51: 12 | F51: — | G51: =成本与现售价!$I$51 -> 4.6656 | H51: =MIN(0.95,MAX(费率与参数!$B$6,费率与参数!$B$5-(费率与参数!$B$5-费率与参数!$B$6)*(LN(MAX(G51,0.01))-LN(MIN(成本与现售价!$I$4:$I$172)))/(LN(MAX(成本与现售价!$I$4:$I$172))-LN(MIN(成本与现售价!$I$4:$I$172))))) -> 0.34002301 | I51: =CEILING(G51/(1-H51)/费率与参数!$B$2,费率与参数!$B$3)*费率与参数!$B$2 -> 7.07 | J51: =I51/费率与参数!$B$2 -> 707 | K51: =1-G51/I51 -> 0.34008487 | L51: =成本与现售价!$J$51 -> 467 | M51: =I51/成本与现售价!$K$51-1 -> 0.51391863
A52: Seedance 2.0 Mini（极速版） | B52: Ark官方 | C52: doubao-seedance-2-0-mini-260615 | D52: 720p | E52: 13 | F52: — | G52: =成本与现售价!$I$52 -> 5.0544 | H52: =MIN(0.95,MAX(费率与参数!$B$6,费率与参数!$B$5-(费率与参数!$B$5-费率与参数!$B$6)*(LN(MAX(G52,0.01))-LN(MIN(成本与现售价!$I$4:$I$172)))/(LN(MAX(成本与现售价!$I$4:$I$172))-LN(MIN(成本与现售价!$I$4:$I$172))))) -> 0.33448984 | I52: =CEILING(G52/(1-H52)/费率与参数!$B$2,费率与参数!$B$3)*费率与参数!$B$2 -> 7.6 | J52: =I52/费率与参数!$B$2 -> 760 | K52: =1-G52/I52 -> 0.33494737 | L52: =成本与现售价!$J$52 -> 506 | M52: =I52/成本与现售价!$K$52-1 -> 0.50197628
A53: Seedance 2.0 Mini（极速版） | B53: Ark官方 | C53: doubao-seedance-2-0-mini-260615 | D53: 720p | E53: 14 | F53: — | G53: =成本与现售价!$I$53 -> 5.4432 | H53: =MIN(0.95,MAX(费率与参数!$B$6,费率与参数!$B$5-(费率与参数!$B$5-费率与参数!$B$6)*(LN(MAX(G53,0.01))-LN(MIN(成本与现售价!$I$4:$I$172)))/(LN(MAX(成本与现售价!$I$4:$I$172))-LN(MIN(成本与现售价!$I$4:$I$172))))) -> 0.32936694 | I53: =CEILING(G53/(1-H53)/费率与参数!$B$2,费率与参数!$B$3)*费率与参数!$B$2 -> 8.12 | J53: =I53/费率与参数!$B$2 -> 812 | K53: =1-G53/I53 -> 0.32965517 | L53: =成本与现售价!$J$53 -> 545 | M53: =I53/成本与现售价!$K$53-1 -> 0.48990826
A54: Seedance 2.0 Mini（极速版） | B54: Ark官方 | C54: doubao-seedance-2-0-mini-260615 | D54: 720p | E54: 15 | F54: — | G54: =成本与现售价!$I$54 -> 5.832 | H54: =MIN(0.95,MAX(费率与参数!$B$6,费率与参数!$B$5-(费率与参数!$B$5-费率与参数!$B$6)*(LN(MAX(G54,0.01))-LN(MIN(成本与现售价!$I$4:$I$172)))/(LN(MAX(成本与现售价!$I$4:$I$172))-LN(MIN(成本与现售价!$I$4:$I$172))))) -> 0.32459762 | I54: =CEILING(G54/(1-H54)/费率与参数!$B$2,费率与参数!$B$3)*费率与参数!$B$2 -> 8.64 | J54: =I54/费率与参数!$B$2 -> 864 | K54: =1-G54/I54 -> 0.325 | L54: =成本与现售价!$J$54 -> 584 | M54: =I54/成本与现售价!$K$54-1 -> 0.47945205
A55: Seedance 2.0 Mini（极速版） | B55: Ark官方 | C55: doubao-seedance-2-0-mini-260615 | D55: 1080p | E55: 4 | F55: — | G55: =成本与现售价!$I$55 -> 5.832 | H55: =MIN(0.95,MAX(费率与参数!$B$6,费率与参数!$B$5-(费率与参数!$B$5-费率与参数!$B$6)*(LN(MAX(G55,0.01))-LN(MIN(成本与现售价!$I$4:$I$172)))/(LN(MAX(成本与现售价!$I$4:$I$172))-LN(MIN(成本与现售价!$I$4:$I$172))))) -> 0.32459762 | I55: =CEILING(G55/(1-H55)/费率与参数!$B$2,费率与参数!$B$3)*费率与参数!$B$2 -> 8.64 | J55: =I55/费率与参数!$B$2 -> 864 | K55: =1-G55/I55 -> 0.325 | L55: =成本与现售价!$J$55 -> 584 | M55: =I55/成本与现售价!$K$55-1 -> 0.47945205
A56: Seedance 2.0 Mini（极速版） | B56: Ark官方 | C56: doubao-seedance-2-0-mini-260615 | D56: 1080p | E56: 5 | F56: — | G56: =成本与现售价!$I$56 -> 7.29 | H56: =MIN(0.95,MAX(费率与参数!$B$6,费率与参数!$B$5-(费率与参数!$B$5-费率与参数!$B$6)*(LN(MAX(G56,0.01))-LN(MIN(成本与现售价!$I$4:$I$172)))/(LN(MAX(成本与现售价!$I$4:$I$172))-LN(MIN(成本与现售价!$I$4:$I$172))))) -> 0.30917224 | I56: =CEILING(G56/(1-H56)/费率与参数!$B$2,费率与参数!$B$3)*费率与参数!$B$2 -> 10.56 | J56: =I56/费率与参数!$B$2 -> 1056 | K56: =1-G56/I56 -> 0.30965909 | L56: =成本与现售价!$J$56 -> 729 | M56: =I56/成本与现售价!$K$56-1 -> 0.44855967
A57: Seedance 2.0 Mini（极速版） | B57: Ark官方 | C57: doubao-seedance-2-0-mini-260615 | D57: 1080p | E57: 6 | F57: — | G57: =成本与现售价!$I$57 -> 8.748 | H57: =MIN(0.95,MAX(费率与参数!$B$6,费率与参数!$B$5-(费率与参数!$B$5-费率与参数!$B$6)*(LN(MAX(G57,0.01))-LN(MIN(成本与现售价!$I$4:$I$172)))/(LN(MAX(成本与现售价!$I$4:$I$172))-LN(MIN(成本与现售价!$I$4:$I$172))))) -> 0.29656878 | I57: =CEILING(G57/(1-H57)/费率与参数!$B$2,费率与参数!$B$3)*费率与参数!$B$2 -> 12.44 | J57: =I57/费率与参数!$B$2 -> 1244 | K57: =1-G57/I57 -> 0.29678457 | L57: =成本与现售价!$J$57 -> 875 | M57: =I57/成本与现售价!$K$57-1 -> 0.42171429
A58: Seedance 2.0 Mini（极速版） | B58: Ark官方 | C58: doubao-seedance-2-0-mini-260615 | D58: 1080p | E58: 7 | F58: — | G58: =成本与现售价!$I$58 -> 10.206 | H58: =MIN(0.95,MAX(费率与参数!$B$6,费率与参数!$B$5-(费率与参数!$B$5-费率与参数!$B$6)*(LN(MAX(G58,0.01))-LN(MIN(成本与现售价!$I$4:$I$172)))/(LN(MAX(成本与现售价!$I$4:$I$172))-LN(MIN(成本与现售价!$I$4:$I$172))))) -> 0.28591271 | I58: =CEILING(G58/(1-H58)/费率与参数!$B$2,费率与参数!$B$3)*费率与参数!$B$2 -> 14.3 | J58: =I58/费率与参数!$B$2 -> 1430 | K58: =1-G58/I58 -> 0.28629371 | L58: =成本与现售价!$J$58 -> 1021 | M58: =I58/成本与现售价!$K$58-1 -> 0.40058766
A59: Seedance 2.0 Mini（极速版） | B59: Ark官方 | C59: doubao-seedance-2-0-mini-260615 | D59: 1080p | E59: 8 | F59: — | G59: =成本与现售价!$I$59 -> 11.664 | H59: =MIN(0.95,MAX(费率与参数!$B$6,费率与参数!$B$5-(费率与参数!$B$5-费率与参数!$B$6)*(LN(MAX(G59,0.01))-LN(MIN(成本与现售价!$I$4:$I$172)))/(LN(MAX(成本与现售价!$I$4:$I$172))-LN(MIN(成本与现售价!$I$4:$I$172))))) -> 0.276682 | I59: =CEILING(G59/(1-H59)/费率与参数!$B$2,费率与参数!$B$3)*费率与参数!$B$2 -> 16.13 | J59: =I59/费率与参数!$B$2 -> 1613 | K59: =1-G59/I59 -> 0.27687539 | L59: =成本与现售价!$J$59 -> 1167 | M59: =I59/成本与现售价!$K$59-1 -> 0.38217652
A60: Seedance 2.0 Mini（极速版） | B60: Ark官方 | C60: doubao-seedance-2-0-mini-260615 | D60: 1080p | E60: 9 | F60: — | G60: =成本与现售价!$I$60 -> 13.122 | H60: =MIN(0.95,MAX(费率与参数!$B$6,费率与参数!$B$5-(费率与参数!$B$5-费率与参数!$B$6)*(LN(MAX(G60,0.01))-LN(MIN(成本与现售价!$I$4:$I$172)))/(LN(MAX(成本与现售价!$I$4:$I$172))-LN(MIN(成本与现售价!$I$4:$I$172))))) -> 0.26853994 | I60: =CEILING(G60/(1-H60)/费率与参数!$B$2,费率与参数!$B$3)*费率与参数!$B$2 -> 17.94 | J60: =I60/费率与参数!$B$2 -> 1794 | K60: =1-G60/I60 -> 0.26856187 | L60: =成本与现售价!$J$60 -> 1313 | M60: =I60/成本与现售价!$K$60-1 -> 0.36633663
A61: Seedance 2.0 Mini（极速版） | B61: Ark官方 | C61: doubao-seedance-2-0-mini-260615 | D61: 1080p | E61: 10 | F61: — | G61: =成本与现售价!$I$61 -> 14.58 | H61: =MIN(0.95,MAX(费率与参数!$B$6,费率与参数!$B$5-(费率与参数!$B$5-费率与参数!$B$6)*(LN(MAX(G61,0.01))-LN(MIN(成本与现售价!$I$4:$I$172)))/(LN(MAX(成本与现售价!$I$4:$I$172))-LN(MIN(成本与现售价!$I$4:$I$172))))) -> 0.26125662 | I61: =CEILING(G61/(1-H61)/费率与参数!$B$2,费率与参数!$B$3)*费率与参数!$B$2 -> 19.74 | J61: =I61/费率与参数!$B$2 -> 1974 | K61: =1-G61/I61 -> 0.26139818 | L61: =成本与现售价!$J$61 -> 1458 | M61: =I61/成本与现售价!$K$61-1 -> 0.35390947
A62: Seedance 2.0 Mini（极速版） | B62: Ark官方 | C62: doubao-seedance-2-0-mini-260615 | D62: 1080p | E62: 11 | F62: — | G62: =成本与现售价!$I$62 -> 16.038 | H62: =MIN(0.95,MAX(费率与参数!$B$6,费率与参数!$B$5-(费率与参数!$B$5-费率与参数!$B$6)*(LN(MAX(G62,0.01))-LN(MIN(成本与现售价!$I$4:$I$172)))/(LN(MAX(成本与现售价!$I$4:$I$172))-LN(MIN(成本与现售价!$I$4:$I$172))))) -> 0.25466805 | I62: =CEILING(G62/(1-H62)/费率与参数!$B$2,费率与参数!$B$3)*费率与参数!$B$2 -> 21.52 | J62: =I62/费率与参数!$B$2 -> 2152 | K62: =1-G62/I62 -> 0.25473978 | L62: =成本与现售价!$J$62 -> 1604 | M62: =I62/成本与现售价!$K$62-1 -> 0.34164589
A63: Seedance 2.0 Mini（极速版） | B63: Ark官方 | C63: doubao-seedance-2-0-mini-260615 | D63: 1080p | E63: 12 | F63: — | G63: =成本与现售价!$I$63 -> 17.496 | H63: =MIN(0.95,MAX(费率与参数!$B$6,费率与参数!$B$5-(费率与参数!$B$5-费率与参数!$B$6)*(LN(MAX(G63,0.01))-LN(MIN(成本与现售价!$I$4:$I$172)))/(LN(MAX(成本与现售价!$I$4:$I$172))-LN(MIN(成本与现售价!$I$4:$I$172))))) -> 0.24865316 | I63: =CEILING(G63/(1-H63)/费率与参数!$B$2,费率与参数!$B$3)*费率与参数!$B$2 -> 23.29 | J63: =I63/费率与参数!$B$2 -> 2329 | K63: =1-G63/I63 -> 0.2487763 | L63: =成本与现售价!$J$63 -> 1750 | M63: =I63/成本与现售价!$K$63-1 -> 0.33085714
A64: Seedance 2.0 Mini（极速版） | B64: Ark官方 | C64: doubao-seedance-2-0-mini-260615 | D64: 1080p | E64: 13 | F64: — | G64: =成本与现售价!$I$64 -> 18.954 | H64: =MIN(0.95,MAX(费率与参数!$B$6,费率与参数!$B$5-(费率与参数!$B$5-费率与参数!$B$6)*(LN(MAX(G64,0.01))-LN(MIN(成本与现售价!$I$4:$I$172)))/(LN(MAX(成本与现售价!$I$4:$I$172))-LN(MIN(成本与现售价!$I$4:$I$172))))) -> 0.24312 | I64: =CEILING(G64/(1-H64)/费率与参数!$B$2,费率与参数!$B$3)*费率与参数!$B$2 -> 25.05 | J64: =I64/费率与参数!$B$2 -> 2505 | K64: =1-G64/I64 -> 0.24335329 | L64: =成本与现售价!$J$64 -> 1896 | M64: =I64/成本与现售价!$K$64-1 -> 0.32120253
A65: Seedance 2.0 Mini（极速版） | B65: Ark官方 | C65: doubao-seedance-2-0-mini-260615 | D65: 1080p | E65: 14 | F65: — | G65: =成本与现售价!$I$65 -> 20.412 | H65: =MIN(0.95,MAX(费率与参数!$B$6,费率与参数!$B$5-(费率与参数!$B$5-费率与参数!$B$6)*(LN(MAX(G65,0.01))-LN(MIN(成本与现售价!$I$4:$I$172)))/(LN(MAX(成本与现售价!$I$4:$I$172))-LN(MIN(成本与现售价!$I$4:$I$172))))) -> 0.23799709 | I65: =CEILING(G65/(1-H65)/费率与参数!$B$2,费率与参数!$B$3)*费率与参数!$B$2 -> 26.79 | J65: =I65/费率与参数!$B$2 -> 2679 | K65: =1-G65/I65 -> 0.23807391 | L65: =成本与现售价!$J$65 -> 2042 | M65: =I65/成本与现售价!$K$65-1 -> 0.31194907
A66: Seedance 2.0 Mini（极速版） | B66: Ark官方 | C66: doubao-seedance-2-0-mini-260615 | D66: 1080p | E66: 15 | F66: — | G66: =成本与现售价!$I$66 -> 21.87 | H66: =MIN(0.95,MAX(费率与参数!$B$6,费率与参数!$B$5-(费率与参数!$B$5-费率与参数!$B$6)*(LN(MAX(G66,0.01))-LN(MIN(成本与现售价!$I$4:$I$172)))/(LN(MAX(成本与现售价!$I$4:$I$172))-LN(MIN(成本与现售价!$I$4:$I$172))))) -> 0.23322778 | I66: =CEILING(G66/(1-H66)/费率与参数!$B$2,费率与参数!$B$3)*费率与参数!$B$2 -> 28.53 | J66: =I66/费率与参数!$B$2 -> 2853 | K66: =1-G66/I66 -> 0.23343849 | L66: =成本与现售价!$J$66 -> 2187 | M66: =I66/成本与现售价!$K$66-1 -> 0.30452675
A67: MiniMax H3（海螺） | B67: MiniMax官方 | C67: MiniMax-H3 | D67: 768p | E67: 4 | F67: 0 | G67: =成本与现售价!$I$67 -> 2 | H67: =MIN(0.95,MAX(费率与参数!$B$6,费率与参数!$B$5-(费率与参数!$B$5-费率与参数!$B$6)*(LN(MAX(G67,0.01))-LN(MIN(成本与现售价!$I$4:$I$172)))/(LN(MAX(成本与现售价!$I$4:$I$172))-LN(MIN(成本与现售价!$I$4:$I$172))))) -> 0.39857889 | I67: =CEILING(G67/(1-H67)/费率与参数!$B$2,费率与参数!$B$3)*费率与参数!$B$2 -> 3.33 | J67: =I67/费率与参数!$B$2 -> 333 | K67: =1-G67/I67 -> 0.3993994 | L67: =成本与现售价!$J$67 -> 200 | M67: =I67/成本与现售价!$K$67-1 -> 0.665
A68: MiniMax H3（海螺） | B68: MiniMax官方 | C68: MiniMax-H3 | D68: 768p | E68: 5 | F68: 0 | G68: =成本与现售价!$I$68 -> 2.5 | H68: =MIN(0.95,MAX(费率与参数!$B$6,费率与参数!$B$5-(费率与参数!$B$5-费率与参数!$B$6)*(LN(MAX(G68,0.01))-LN(MIN(成本与现售价!$I$4:$I$172)))/(LN(MAX(成本与现售价!$I$4:$I$172))-LN(MIN(成本与现售价!$I$4:$I$172))))) -> 0.38315351 | I68: =CEILING(G68/(1-H68)/费率与参数!$B$2,费率与参数!$B$3)*费率与参数!$B$2 -> 4.06 | J68: =I68/费率与参数!$B$2 -> 406 | K68: =1-G68/I68 -> 0.38423645 | L68: =成本与现售价!$J$68 -> 250 | M68: =I68/成本与现售价!$K$68-1 -> 0.624
A69: MiniMax H3（海螺） | B69: MiniMax官方 | C69: MiniMax-H3 | D69: 768p | E69: 6 | F69: 0 | G69: =成本与现售价!$I$69 -> 3 | H69: =MIN(0.95,MAX(费率与参数!$B$6,费率与参数!$B$5-(费率与参数!$B$5-费率与参数!$B$6)*(LN(MAX(G69,0.01))-LN(MIN(成本与现售价!$I$4:$I$172)))/(LN(MAX(成本与现售价!$I$4:$I$172))-LN(MIN(成本与现售价!$I$4:$I$172))))) -> 0.37055005 | I69: =CEILING(G69/(1-H69)/费率与参数!$B$2,费率与参数!$B$3)*费率与参数!$B$2 -> 4.77 | J69: =I69/费率与参数!$B$2 -> 477 | K69: =1-G69/I69 -> 0.37106918 | L69: =成本与现售价!$J$69 -> 300 | M69: =I69/成本与现售价!$K$69-1 -> 0.59
A70: MiniMax H3（海螺） | B70: MiniMax官方 | C70: MiniMax-H3 | D70: 768p | E70: 7 | F70: 0 | G70: =成本与现售价!$I$70 -> 3.5 | H70: =MIN(0.95,MAX(费率与参数!$B$6,费率与参数!$B$5-(费率与参数!$B$5-费率与参数!$B$6)*(LN(MAX(G70,0.01))-LN(MIN(成本与现售价!$I$4:$I$172)))/(LN(MAX(成本与现售价!$I$4:$I$172))-LN(MIN(成本与现售价!$I$4:$I$172))))) -> 0.35989398 | I70: =CEILING(G70/(1-H70)/费率与参数!$B$2,费率与参数!$B$3)*费率与参数!$B$2 -> 5.47 | J70: =I70/费率与参数!$B$2 -> 547 | K70: =1-G70/I70 -> 0.36014625 | L70: =成本与现售价!$J$70 -> 350 | M70: =I70/成本与现售价!$K$70-1 -> 0.56285714
A71: MiniMax H3（海螺） | B71: MiniMax官方 | C71: MiniMax-H3 | D71: 768p | E71: 8 | F71: 0 | G71: =成本与现售价!$I$71 -> 4 | H71: =MIN(0.95,MAX(费率与参数!$B$6,费率与参数!$B$5-(费率与参数!$B$5-费率与参数!$B$6)*(LN(MAX(G71,0.01))-LN(MIN(成本与现售价!$I$4:$I$172)))/(LN(MAX(成本与现售价!$I$4:$I$172))-LN(MIN(成本与现售价!$I$4:$I$172))))) -> 0.35066327 | I71: =CEILING(G71/(1-H71)/费率与参数!$B$2,费率与参数!$B$3)*费率与参数!$B$2 -> 6.17 | J71: =I71/费率与参数!$B$2 -> 617 | K71: =1-G71/I71 -> 0.35170178 | L71: =成本与现售价!$J$71 -> 400 | M71: =I71/成本与现售价!$K$71-1 -> 0.5425
A72: MiniMax H3（海螺） | B72: MiniMax官方 | C72: MiniMax-H3 | D72: 768p | E72: 9 | F72: 0 | G72: =成本与现售价!$I$72 -> 4.5 | H72: =MIN(0.95,MAX(费率与参数!$B$6,费率与参数!$B$5-(费率与参数!$B$5-费率与参数!$B$6)*(LN(MAX(G72,0.01))-LN(MIN(成本与现售价!$I$4:$I$172)))/(LN(MAX(成本与现售价!$I$4:$I$172))-LN(MIN(成本与现售价!$I$4:$I$172))))) -> 0.34252121 | I72: =CEILING(G72/(1-H72)/费率与参数!$B$2,费率与参数!$B$3)*费率与参数!$B$2 -> 6.85 | J72: =I72/费率与参数!$B$2 -> 685 | K72: =1-G72/I72 -> 0.34306569 | L72: =成本与现售价!$J$72 -> 450 | M72: =I72/成本与现售价!$K$72-1 -> 0.52222222
A73: MiniMax H3（海螺） | B73: MiniMax官方 | C73: MiniMax-H3 | D73: 768p | E73: 10 | F73: 0 | G73: =成本与现售价!$I$73 -> 5 | H73: =MIN(0.95,MAX(费率与参数!$B$6,费率与参数!$B$5-(费率与参数!$B$5-费率与参数!$B$6)*(LN(MAX(G73,0.01))-LN(MIN(成本与现售价!$I$4:$I$172)))/(LN(MAX(成本与现售价!$I$4:$I$172))-LN(MIN(成本与现售价!$I$4:$I$172))))) -> 0.33523789 | I73: =CEILING(G73/(1-H73)/费率与参数!$B$2,费率与参数!$B$3)*费率与参数!$B$2 -> 7.53 | J73: =I73/费率与参数!$B$2 -> 753 | K73: =1-G73/I73 -> 0.33598938 | L73: =成本与现售价!$J$73 -> 500 | M73: =I73/成本与现售价!$K$73-1 -> 0.506
A74: MiniMax H3（海螺） | B74: MiniMax官方 | C74: MiniMax-H3 | D74: 768p | E74: 11 | F74: 0 | G74: =成本与现售价!$I$74 -> 5.5 | H74: =MIN(0.95,MAX(费率与参数!$B$6,费率与参数!$B$5-(费率与参数!$B$5-费率与参数!$B$6)*(LN(MAX(G74,0.01))-LN(MIN(成本与现售价!$I$4:$I$172)))/(LN(MAX(成本与现售价!$I$4:$I$172))-LN(MIN(成本与现售价!$I$4:$I$172))))) -> 0.32864932 | I74: =CEILING(G74/(1-H74)/费率与参数!$B$2,费率与参数!$B$3)*费率与参数!$B$2 -> 8.2 | J74: =I74/费率与参数!$B$2 -> 820 | K74: =1-G74/I74 -> 0.32926829 | L74: =成本与现售价!$J$74 -> 550 | M74: =I74/成本与现售价!$K$74-1 -> 0.49090909
A75: MiniMax H3（海螺） | B75: MiniMax官方 | C75: MiniMax-H3 | D75: 768p | E75: 12 | F75: 0 | G75: =成本与现售价!$I$75 -> 6 | H75: =MIN(0.95,MAX(费率与参数!$B$6,费率与参数!$B$5-(费率与参数!$B$5-费率与参数!$B$6)*(LN(MAX(G75,0.01))-LN(MIN(成本与现售价!$I$4:$I$172)))/(LN(MAX(成本与现售价!$I$4:$I$172))-LN(MIN(成本与现售价!$I$4:$I$172))))) -> 0.32263443 | I75: =CEILING(G75/(1-H75)/费率与参数!$B$2,费率与参数!$B$3)*费率与参数!$B$2 -> 8.86 | J75: =I75/费率与参数!$B$2 -> 886 | K75: =1-G75/I75 -> 0.3227991 | L75: =成本与现售价!$J$75 -> 600 | M75: =I75/成本与现售价!$K$75-1 -> 0.47666667
A76: MiniMax H3（海螺） | B76: MiniMax官方 | C76: MiniMax-H3 | D76: 768p | E76: 13 | F76: 0 | G76: =成本与现售价!$I$76 -> 6.5 | H76: =MIN(0.95,MAX(费率与参数!$B$6,费率与参数!$B$5-(费率与参数!$B$5-费率与参数!$B$6)*(LN(MAX(G76,0.01))-LN(MIN(成本与现售价!$I$4:$I$172)))/(LN(MAX(成本与现售价!$I$4:$I$172))-LN(MIN(成本与现售价!$I$4:$I$172))))) -> 0.31710127 | I76: =CEILING(G76/(1-H76)/费率与参数!$B$2,费率与参数!$B$3)*费率与参数!$B$2 -> 9.52 | J76: =I76/费率与参数!$B$2 -> 952 | K76: =1-G76/I76 -> 0.31722689 | L76: =成本与现售价!$J$76 -> 650 | M76: =I76/成本与现售价!$K$76-1 -> 0.46461538
A77: MiniMax H3（海螺） | B77: MiniMax官方 | C77: MiniMax-H3 | D77: 768p | E77: 14 | F77: 0 | G77: =成本与现售价!$I$77 -> 7 | H77: =MIN(0.95,MAX(费率与参数!$B$6,费率与参数!$B$5-(费率与参数!$B$5-费率与参数!$B$6)*(LN(MAX(G77,0.01))-LN(MIN(成本与现售价!$I$4:$I$172)))/(LN(MAX(成本与现售价!$I$4:$I$172))-LN(MIN(成本与现售价!$I$4:$I$172))))) -> 0.31197836 | I77: =CEILING(G77/(1-H77)/费率与参数!$B$2,费率与参数!$B$3)*费率与参数!$B$2 -> 10.18 | J77: =I77/费率与参数!$B$2 -> 1018 | K77: =1-G77/I77 -> 0.31237721 | L77: =成本与现售价!$J$77 -> 700 | M77: =I77/成本与现售价!$K$77-1 -> 0.45428571
A78: MiniMax H3（海螺） | B78: MiniMax官方 | C78: MiniMax-H3 | D78: 768p | E78: 15 | F78: 0 | G78: =成本与现售价!$I$78 -> 7.5 | H78: =MIN(0.95,MAX(费率与参数!$B$6,费率与参数!$B$5-(费率与参数!$B$5-费率与参数!$B$6)*(LN(MAX(G78,0.01))-LN(MIN(成本与现售价!$I$4:$I$172)))/(LN(MAX(成本与现售价!$I$4:$I$172))-LN(MIN(成本与现售价!$I$4:$I$172))))) -> 0.30720905 | I78: =CEILING(G78/(1-H78)/费率与参数!$B$2,费率与参数!$B$3)*费率与参数!$B$2 -> 10.83 | J78: =I78/费率与参数!$B$2 -> 1083 | K78: =1-G78/I78 -> 0.30747922 | L78: =成本与现售价!$J$78 -> 750 | M78: =I78/成本与现售价!$K$78-1 -> 0.444
A79: MiniMax H3（海螺） | B79: MiniMax官方 | C79: MiniMax-H3 | D79: 2k | E79: 4 | F79: 0 | G79: =成本与现售价!$I$79 -> 3.2 | H79: =MIN(0.95,MAX(费率与参数!$B$6,费率与参数!$B$5-(费率与参数!$B$5-费率与参数!$B$6)*(LN(MAX(G79,0.01))-LN(MIN(成本与现售价!$I$4:$I$172)))/(LN(MAX(成本与现售价!$I$4:$I$172))-LN(MIN(成本与现售价!$I$4:$I$172))))) -> 0.36608866 | I79: =CEILING(G79/(1-H79)/费率与参数!$B$2,费率与参数!$B$3)*费率与参数!$B$2 -> 5.05 | J79: =I79/费率与参数!$B$2 -> 505 | K79: =1-G79/I79 -> 0.36633663 | L79: =成本与现售价!$J$79 -> 320 | M79: =I79/成本与现售价!$K$79-1 -> 0.578125
A80: MiniMax H3（海螺） | B80: MiniMax官方 | C80: MiniMax-H3 | D80: 2k | E80: 5 | F80: 0 | G80: =成本与现售价!$I$80 -> 4 | H80: =MIN(0.95,MAX(费率与参数!$B$6,费率与参数!$B$5-(费率与参数!$B$5-费率与参数!$B$6)*(LN(MAX(G80,0.01))-LN(MIN(成本与现售价!$I$4:$I$172)))/(LN(MAX(成本与现售价!$I$4:$I$172))-LN(MIN(成本与现售价!$I$4:$I$172))))) -> 0.35066327 | I80: =CEILING(G80/(1-H80)/费率与参数!$B$2,费率与参数!$B$3)*费率与参数!$B$2 -> 6.17 | J80: =I80/费率与参数!$B$2 -> 617 | K80: =1-G80/I80 -> 0.35170178 | L80: =成本与现售价!$J$80 -> 400 | M80: =I80/成本与现售价!$K$80-1 -> 0.5425
A81: MiniMax H3（海螺） | B81: MiniMax官方 | C81: MiniMax-H3 | D81: 2k | E81: 6 | F81: 0 | G81: =成本与现售价!$I$81 -> 4.8 | H81: =MIN(0.95,MAX(费率与参数!$B$6,费率与参数!$B$5-(费率与参数!$B$5-费率与参数!$B$6)*(LN(MAX(G81,0.01))-LN(MIN(成本与现售价!$I$4:$I$172)))/(LN(MAX(成本与现售价!$I$4:$I$172))-LN(MIN(成本与现售价!$I$4:$I$172))))) -> 0.33805982 | I81: =CEILING(G81/(1-H81)/费率与参数!$B$2,费率与参数!$B$3)*费率与参数!$B$2 -> 7.26 | J81: =I81/费率与参数!$B$2 -> 726 | K81: =1-G81/I81 -> 0.33884298 | L81: =成本与现售价!$J$81 -> 480 | M81: =I81/成本与现售价!$K$81-1 -> 0.5125
A82: MiniMax H3（海螺） | B82: MiniMax官方 | C82: MiniMax-H3 | D82: 2k | E82: 7 | F82: 0 | G82: =成本与现售价!$I$82 -> 5.6 | H82: =MIN(0.95,MAX(费率与参数!$B$6,费率与参数!$B$5-(费率与参数!$B$5-费率与参数!$B$6)*(LN(MAX(G82,0.01))-LN(MIN(成本与现售价!$I$4:$I$172)))/(LN(MAX(成本与现售价!$I$4:$I$172))-LN(MIN(成本与现售价!$I$4:$I$172))))) -> 0.32740375 | I82: =CEILING(G82/(1-H82)/费率与参数!$B$2,费率与参数!$B$3)*费率与参数!$B$2 -> 8.33 | J82: =I82/费率与参数!$B$2 -> 833 | K82: =1-G82/I82 -> 0.32773109 | L82: =成本与现售价!$J$82 -> 560 | M82: =I82/成本与现售价!$K$82-1 -> 0.4875
A83: MiniMax H3（海螺） | B83: MiniMax官方 | C83: MiniMax-H3 | D83: 2k | E83: 8 | F83: 0 | G83: =成本与现售价!$I$83 -> 6.4 | H83: =MIN(0.95,MAX(费率与参数!$B$6,费率与参数!$B$5-(费率与参数!$B$5-费率与参数!$B$6)*(LN(MAX(G83,0.01))-LN(MIN(成本与现售价!$I$4:$I$172)))/(LN(MAX(成本与现售价!$I$4:$I$172))-LN(MIN(成本与现售价!$I$4:$I$172))))) -> 0.31817304 | I83: =CEILING(G83/(1-H83)/费率与参数!$B$2,费率与参数!$B$3)*费率与参数!$B$2 -> 9.39 | J83: =I83/费率与参数!$B$2 -> 939 | K83: =1-G83/I83 -> 0.31842386 | L83: =成本与现售价!$J$83 -> 640 | M83: =I83/成本与现售价!$K$83-1 -> 0.4671875
A84: MiniMax H3（海螺） | B84: MiniMax官方 | C84: MiniMax-H3 | D84: 2k | E84: 9 | F84: 0 | G84: =成本与现售价!$I$84 -> 7.2 | H84: =MIN(0.95,MAX(费率与参数!$B$6,费率与参数!$B$5-(费率与参数!$B$5-费率与参数!$B$6)*(LN(MAX(G84,0.01))-LN(MIN(成本与现售价!$I$4:$I$172)))/(LN(MAX(成本与现售价!$I$4:$I$172))-LN(MIN(成本与现售价!$I$4:$I$172))))) -> 0.31003098 | I84: =CEILING(G84/(1-H84)/费率与参数!$B$2,费率与参数!$B$3)*费率与参数!$B$2 -> 10.44 | J84: =I84/费率与参数!$B$2 -> 1044 | K84: =1-G84/I84 -> 0.31034483 | L84: =成本与现售价!$J$84 -> 720 | M84: =I84/成本与现售价!$K$84-1 -> 0.45
A85: MiniMax H3（海螺） | B85: MiniMax官方 | C85: MiniMax-H3 | D85: 2k | E85: 10 | F85: 0 | G85: =成本与现售价!$I$85 -> 8 | H85: =MIN(0.95,MAX(费率与参数!$B$6,费率与参数!$B$5-(费率与参数!$B$5-费率与参数!$B$6)*(LN(MAX(G85,0.01))-LN(MIN(成本与现售价!$I$4:$I$172)))/(LN(MAX(成本与现售价!$I$4:$I$172))-LN(MIN(成本与现售价!$I$4:$I$172))))) -> 0.30274766 | I85: =CEILING(G85/(1-H85)/费率与参数!$B$2,费率与参数!$B$3)*费率与参数!$B$2 -> 11.48 | J85: =I85/费率与参数!$B$2 -> 1148 | K85: =1-G85/I85 -> 0.30313589 | L85: =成本与现售价!$J$85 -> 800 | M85: =I85/成本与现售价!$K$85-1 -> 0.435
A86: MiniMax H3（海螺） | B86: MiniMax官方 | C86: MiniMax-H3 | D86: 2k | E86: 11 | F86: 0 | G86: =成本与现售价!$I$86 -> 8.8 | H86: =MIN(0.95,MAX(费率与参数!$B$6,费率与参数!$B$5-(费率与参数!$B$5-费率与参数!$B$6)*(LN(MAX(G86,0.01))-LN(MIN(成本与现售价!$I$4:$I$172)))/(LN(MAX(成本与现售价!$I$4:$I$172))-LN(MIN(成本与现售价!$I$4:$I$172))))) -> 0.29615909 | I86: =CEILING(G86/(1-H86)/费率与参数!$B$2,费率与参数!$B$3)*费率与参数!$B$2 -> 12.51 | J86: =I86/费率与参数!$B$2 -> 1251 | K86: =1-G86/I86 -> 0.29656275 | L86: =成本与现售价!$J$86 -> 880 | M86: =I86/成本与现售价!$K$86-1 -> 0.42159091
A87: MiniMax H3（海螺） | B87: MiniMax官方 | C87: MiniMax-H3 | D87: 2k | E87: 12 | F87: 0 | G87: =成本与现售价!$I$87 -> 9.6 | H87: =MIN(0.95,MAX(费率与参数!$B$6,费率与参数!$B$5-(费率与参数!$B$5-费率与参数!$B$6)*(LN(MAX(G87,0.01))-LN(MIN(成本与现售价!$I$4:$I$172)))/(LN(MAX(成本与现售价!$I$4:$I$172))-LN(MIN(成本与现售价!$I$4:$I$172))))) -> 0.2901442 | I87: =CEILING(G87/(1-H87)/费率与参数!$B$2,费率与参数!$B$3)*费率与参数!$B$2 -> 13.53 | J87: =I87/费率与参数!$B$2 -> 1353 | K87: =1-G87/I87 -> 0.29046563 | L87: =成本与现售价!$J$87 -> 960 | M87: =I87/成本与现售价!$K$87-1 -> 0.409375
A88: MiniMax H3（海螺） | B88: MiniMax官方 | C88: MiniMax-H3 | D88: 2k | E88: 13 | F88: 0 | G88: =成本与现售价!$I$88 -> 10.4 | H88: =MIN(0.95,MAX(费率与参数!$B$6,费率与参数!$B$5-(费率与参数!$B$5-费率与参数!$B$6)*(LN(MAX(G88,0.01))-LN(MIN(成本与现售价!$I$4:$I$172)))/(LN(MAX(成本与现售价!$I$4:$I$172))-LN(MIN(成本与现售价!$I$4:$I$172))))) -> 0.28461104 | I88: =CEILING(G88/(1-H88)/费率与参数!$B$2,费率与参数!$B$3)*费率与参数!$B$2 -> 14.54 | J88: =I88/费率与参数!$B$2 -> 1454 | K88: =1-G88/I88 -> 0.28473177 | L88: =成本与现售价!$J$88 -> 1040 | M88: =I88/成本与现售价!$K$88-1 -> 0.39807692
A89: MiniMax H3（海螺） | B89: MiniMax官方 | C89: MiniMax-H3 | D89: 2k | E89: 14 | F89: 0 | G89: =成本与现售价!$I$89 -> 11.2 | H89: =MIN(0.95,MAX(费率与参数!$B$6,费率与参数!$B$5-(费率与参数!$B$5-费率与参数!$B$6)*(LN(MAX(G89,0.01))-LN(MIN(成本与现售价!$I$4:$I$172)))/(LN(MAX(成本与现售价!$I$4:$I$172))-LN(MIN(成本与现售价!$I$4:$I$172))))) -> 0.27948813 | I89: =CEILING(G89/(1-H89)/费率与参数!$B$2,费率与参数!$B$3)*费率与参数!$B$2 -> 15.55 | J89: =I89/费率与参数!$B$2 -> 1555 | K89: =1-G89/I89 -> 0.27974277 | L89: =成本与现售价!$J$89 -> 1120 | M89: =I89/成本与现售价!$K$89-1 -> 0.38839286
A90: MiniMax H3（海螺） | B90: MiniMax官方 | C90: MiniMax-H3 | D90: 2k | E90: 15 | F90: 0 | G90: =成本与现售价!$I$90 -> 12 | H90: =MIN(0.95,MAX(费率与参数!$B$6,费率与参数!$B$5-(费率与参数!$B$5-费率与参数!$B$6)*(LN(MAX(G90,0.01))-LN(MIN(成本与现售价!$I$4:$I$172)))/(LN(MAX(成本与现售价!$I$4:$I$172))-LN(MIN(成本与现售价!$I$4:$I$172))))) -> 0.27471882 | I90: =CEILING(G90/(1-H90)/费率与参数!$B$2,费率与参数!$B$3)*费率与参数!$B$2 -> 16.55 | J90: =I90/费率与参数!$B$2 -> 1655 | K90: =1-G90/I90 -> 0.27492447 | L90: =成本与现售价!$J$90 -> 1200 | M90: =I90/成本与现售价!$K$90-1 -> 0.37916667
A91: MiniMax H3-Max（海螺） | B91: MiniMax官方 | C91: MiniMax-H3-Max | D91: 480p | E91: 5 | F91: 0 | G91: =成本与现售价!$I$91 -> 2.5 | H91: =MIN(0.95,MAX(费率与参数!$B$6,费率与参数!$B$5-(费率与参数!$B$5-费率与参数!$B$6)*(LN(MAX(G91,0.01))-LN(MIN(成本与现售价!$I$4:$I$172)))/(LN(MAX(成本与现售价!$I$4:$I$172))-LN(MIN(成本与现售价!$I$4:$I$172))))) -> 0.38315351 | I91: =CEILING(G91/(1-H91)/费率与参数!$B$2,费率与参数!$B$3)*费率与参数!$B$2 -> 4.06 | J91: =I91/费率与参数!$B$2 -> 406 | K91: =1-G91/I91 -> 0.38423645 | L91: =成本与现售价!$J$91 -> 250 | M91: =I91/成本与现售价!$K$91-1 -> 0.624
A92: MiniMax H3-Max（海螺） | B92: MiniMax官方 | C92: MiniMax-H3-Max | D92: 480p | E92: 6 | F92: 0 | G92: =成本与现售价!$I$92 -> 3 | H92: =MIN(0.95,MAX(费率与参数!$B$6,费率与参数!$B$5-(费率与参数!$B$5-费率与参数!$B$6)*(LN(MAX(G92,0.01))-LN(MIN(成本与现售价!$I$4:$I$172)))/(LN(MAX(成本与现售价!$I$4:$I$172))-LN(MIN(成本与现售价!$I$4:$I$172))))) -> 0.37055005 | I92: =CEILING(G92/(1-H92)/费率与参数!$B$2,费率与参数!$B$3)*费率与参数!$B$2 -> 4.77 | J92: =I92/费率与参数!$B$2 -> 477 | K92: =1-G92/I92 -> 0.37106918 | L92: =成本与现售价!$J$92 -> 300 | M92: =I92/成本与现售价!$K$92-1 -> 0.59
A93: MiniMax H3-Max（海螺） | B93: MiniMax官方 | C93: MiniMax-H3-Max | D93: 480p | E93: 7 | F93: 0 | G93: =成本与现售价!$I$93 -> 3.5 | H93: =MIN(0.95,MAX(费率与参数!$B$6,费率与参数!$B$5-(费率与参数!$B$5-费率与参数!$B$6)*(LN(MAX(G93,0.01))-LN(MIN(成本与现售价!$I$4:$I$172)))/(LN(MAX(成本与现售价!$I$4:$I$172))-LN(MIN(成本与现售价!$I$4:$I$172))))) -> 0.35989398 | I93: =CEILING(G93/(1-H93)/费率与参数!$B$2,费率与参数!$B$3)*费率与参数!$B$2 -> 5.47 | J93: =I93/费率与参数!$B$2 -> 547 | K93: =1-G93/I93 -> 0.36014625 | L93: =成本与现售价!$J$93 -> 350 | M93: =I93/成本与现售价!$K$93-1 -> 0.56285714
A94: MiniMax H3-Max（海螺） | B94: MiniMax官方 | C94: MiniMax-H3-Max | D94: 480p | E94: 8 | F94: 0 | G94: =成本与现售价!$I$94 -> 4 | H94: =MIN(0.95,MAX(费率与参数!$B$6,费率与参数!$B$5-(费率与参数!$B$5-费率与参数!$B$6)*(LN(MAX(G94,0.01))-LN(MIN(成本与现售价!$I$4:$I$172)))/(LN(MAX(成本与现售价!$I$4:$I$172))-LN(MIN(成本与现售价!$I$4:$I$172))))) -> 0.35066327 | I94: =CEILING(G94/(1-H94)/费率与参数!$B$2,费率与参数!$B$3)*费率与参数!$B$2 -> 6.17 | J94: =I94/费率与参数!$B$2 -> 617 | K94: =1-G94/I94 -> 0.35170178 | L94: =成本与现售价!$J$94 -> 400 | M94: =I94/成本与现售价!$K$94-1 -> 0.5425
A95: MiniMax H3-Max（海螺） | B95: MiniMax官方 | C95: MiniMax-H3-Max | D95: 480p | E95: 9 | F95: 0 | G95: =成本与现售价!$I$95 -> 4.5 | H95: =MIN(0.95,MAX(费率与参数!$B$6,费率与参数!$B$5-(费率与参数!$B$5-费率与参数!$B$6)*(LN(MAX(G95,0.01))-LN(MIN(成本与现售价!$I$4:$I$172)))/(LN(MAX(成本与现售价!$I$4:$I$172))-LN(MIN(成本与现售价!$I$4:$I$172))))) -> 0.34252121 | I95: =CEILING(G95/(1-H95)/费率与参数!$B$2,费率与参数!$B$3)*费率与参数!$B$2 -> 6.85 | J95: =I95/费率与参数!$B$2 -> 685 | K95: =1-G95/I95 -> 0.34306569 | L95: =成本与现售价!$J$95 -> 450 | M95: =I95/成本与现售价!$K$95-1 -> 0.52222222
A96: MiniMax H3-Max（海螺） | B96: MiniMax官方 | C96: MiniMax-H3-Max | D96: 480p | E96: 10 | F96: 0 | G96: =成本与现售价!$I$96 -> 5 | H96: =MIN(0.95,MAX(费率与参数!$B$6,费率与参数!$B$5-(费率与参数!$B$5-费率与参数!$B$6)*(LN(MAX(G96,0.01))-LN(MIN(成本与现售价!$I$4:$I$172)))/(LN(MAX(成本与现售价!$I$4:$I$172))-LN(MIN(成本与现售价!$I$4:$I$172))))) -> 0.33523789 | I96: =CEILING(G96/(1-H96)/费率与参数!$B$2,费率与参数!$B$3)*费率与参数!$B$2 -> 7.53 | J96: =I96/费率与参数!$B$2 -> 753 | K96: =1-G96/I96 -> 0.33598938 | L96: =成本与现售价!$J$96 -> 500 | M96: =I96/成本与现售价!$K$96-1 -> 0.506
A97: MiniMax H3-Max（海螺） | B97: MiniMax官方 | C97: MiniMax-H3-Max | D97: 480p | E97: 11 | F97: 0 | G97: =成本与现售价!$I$97 -> 5.5 | H97: =MIN(0.95,MAX(费率与参数!$B$6,费率与参数!$B$5-(费率与参数!$B$5-费率与参数!$B$6)*(LN(MAX(G97,0.01))-LN(MIN(成本与现售价!$I$4:$I$172)))/(LN(MAX(成本与现售价!$I$4:$I$172))-LN(MIN(成本与现售价!$I$4:$I$172))))) -> 0.32864932 | I97: =CEILING(G97/(1-H97)/费率与参数!$B$2,费率与参数!$B$3)*费率与参数!$B$2 -> 8.2 | J97: =I97/费率与参数!$B$2 -> 820 | K97: =1-G97/I97 -> 0.32926829 | L97: =成本与现售价!$J$97 -> 550 | M97: =I97/成本与现售价!$K$97-1 -> 0.49090909
A98: MiniMax H3-Max（海螺） | B98: MiniMax官方 | C98: MiniMax-H3-Max | D98: 480p | E98: 12 | F98: 0 | G98: =成本与现售价!$I$98 -> 6 | H98: =MIN(0.95,MAX(费率与参数!$B$6,费率与参数!$B$5-(费率与参数!$B$5-费率与参数!$B$6)*(LN(MAX(G98,0.01))-LN(MIN(成本与现售价!$I$4:$I$172)))/(LN(MAX(成本与现售价!$I$4:$I$172))-LN(MIN(成本与现售价!$I$4:$I$172))))) -> 0.32263443 | I98: =CEILING(G98/(1-H98)/费率与参数!$B$2,费率与参数!$B$3)*费率与参数!$B$2 -> 8.86 | J98: =I98/费率与参数!$B$2 -> 886 | K98: =1-G98/I98 -> 0.3227991 | L98: =成本与现售价!$J$98 -> 600 | M98: =I98/成本与现售价!$K$98-1 -> 0.47666667
A99: MiniMax H3-Max（海螺） | B99: MiniMax官方 | C99: MiniMax-H3-Max | D99: 480p | E99: 13 | F99: 0 | G99: =成本与现售价!$I$99 -> 6.5 | H99: =MIN(0.95,MAX(费率与参数!$B$6,费率与参数!$B$5-(费率与参数!$B$5-费率与参数!$B$6)*(LN(MAX(G99,0.01))-LN(MIN(成本与现售价!$I$4:$I$172)))/(LN(MAX(成本与现售价!$I$4:$I$172))-LN(MIN(成本与现售价!$I$4:$I$172))))) -> 0.31710127 | I99: =CEILING(G99/(1-H99)/费率与参数!$B$2,费率与参数!$B$3)*费率与参数!$B$2 -> 9.52 | J99: =I99/费率与参数!$B$2 -> 952 | K99: =1-G99/I99 -> 0.31722689 | L99: =成本与现售价!$J$99 -> 650 | M99: =I99/成本与现售价!$K$99-1 -> 0.46461538
A100: MiniMax H3-Max（海螺） | B100: MiniMax官方 | C100: MiniMax-H3-Max | D100: 480p | E100: 14 | F100: 0 | G100: =成本与现售价!$I$100 -> 7 | H100: =MIN(0.95,MAX(费率与参数!$B$6,费率与参数!$B$5-(费率与参数!$B$5-费率与参数!$B$6)*(LN(MAX(G100,0.01))-LN(MIN(成本与现售价!$I$4:$I$172)))/(LN(MAX(成本与现售价!$I$4:$I$172))-LN(MIN(成本与现售价!$I$4:$I$172))))) -> 0.31197836 | I100: =CEILING(G100/(1-H100)/费率与参数!$B$2,费率与参数!$B$3)*费率与参数!$B$2 -> 10.18 | J100: =I100/费率与参数!$B$2 -> 1018 | K100: =1-G100/I100 -> 0.31237721 | L100: =成本与现售价!$J$100 -> 700 | M100: =I100/成本与现售价!$K$100-1 -> 0.45428571
A101: MiniMax H3-Max（海螺） | B101: MiniMax官方 | C101: MiniMax-H3-Max | D101: 480p | E101: 15 | F101: 0 | G101: =成本与现售价!$I$101 -> 7.5 | H101: =MIN(0.95,MAX(费率与参数!$B$6,费率与参数!$B$5-(费率与参数!$B$5-费率与参数!$B$6)*(LN(MAX(G101,0.01))-LN(MIN(成本与现售价!$I$4:$I$172)))/(LN(MAX(成本与现售价!$I$4:$I$172))-LN(MIN(成本与现售价!$I$4:$I$172))))) -> 0.30720905 | I101: =CEILING(G101/(1-H101)/费率与参数!$B$2,费率与参数!$B$3)*费率与参数!$B$2 -> 10.83 | J101: =I101/费率与参数!$B$2 -> 1083 | K101: =1-G101/I101 -> 0.30747922 | L101: =成本与现售价!$J$101 -> 750 | M101: =I101/成本与现售价!$K$101-1 -> 0.444
...

Sheet 利润率曲线
A1: 利润率曲线（X=单条成本元，Y=建议毛利率；每条线是一个“路由×分辨率”，随成本升高从 80% 平滑降到 40%）
A3: 系列 | B3: 成本(元) | C3: 毛利率
A4: Wan3.0 480p | B4: =建议售价清单!G113 -> 1.5 | C4: =建议售价清单!K113 -> 0.41860465
A5: Wan3.0 480p | B5: =建议售价清单!G114 -> 3 | C5: =建议售价清单!K114 -> 0.37106918
A6: Wan3.0 480p | B6: =建议售价清单!G115 -> 4.5 | C6: =建议售价清单!K115 -> 0.34306569
A7: Wan3.0 480p | B7: =建议售价清单!G116 -> 6 | C7: =建议售价清单!K116 -> 0.3227991
A8: Wan3.0 480p | B8: =建议售价清单!G117 -> 9 | C8: =建议售价清单!K117 -> 0.29467085
A9: Wan3.0 480p 编辑延长 | B9: =建议售价清单!G143 -> 3 | C9: =建议售价清单!K143 -> 0.37106918
A10: Wan3.0 480p 编辑延长 | B10: =建议售价清单!G145 -> 4.5 | C10: =建议售价清单!K145 -> 0.34306569
A11: Wan3.0 480p 编辑延长 | B11: =建议售价清单!G147 -> 6 | C11: =建议售价清单!K147 -> 0.3227991
A12: Wan3.0 480p 编辑延长 | B12: =建议售价清单!G149 -> 7.5 | C12: =建议售价清单!K149 -> 0.30747922
A13: Wan3.0 480p 编辑延长 | B13: =建议售价清单!G151 -> 10.5 | C13: =建议售价清单!K151 -> 0.28425358
A14: Wan3.0 720p | B14: =建议售价清单!G118 -> 3 | C14: =建议售价清单!K118 -> 0.37106918
A15: Wan3.0 720p | B15: =建议售价清单!G119 -> 6 | C15: =建议售价清单!K119 -> 0.3227991
A16: Wan3.0 720p | B16: =建议售价清单!G120 -> 9 | C16: =建议售价清单!K120 -> 0.29467085
A17: Wan3.0 720p | B17: =建议售价清单!G121 -> 12 | C17: =建议售价清单!K121 -> 0.27492447
A18: Wan3.0 720p | B18: =建议售价清单!G122 -> 18 | C18: =建议售价清单!K122 -> 0.24686192
A19: Wan3.0 720p 编辑延长 | B19: =建议售价清单!G153 -> 6 | C19: =建议售价清单!K153 -> 0.3227991
A20: Wan3.0 720p 编辑延长 | B20: =建议售价清单!G155 -> 9 | C20: =建议售价清单!K155 -> 0.29467085
A21: Wan3.0 720p 编辑延长 | B21: =建议售价清单!G157 -> 12 | C21: =建议售价清单!K157 -> 0.27492447
A22: Wan3.0 720p 编辑延长 | B22: =建议售价清单!G159 -> 15 | C22: =建议售价清单!K159 -> 0.25962488
A23: Wan3.0 720p 编辑延长 | B23: =建议售价清单!G161 -> 21 | C23: =建议售价清单!K161 -> 0.23608585
A24: Wan3.0 1080p | B24: =建议售价清单!G123 -> 6 | C24: =建议售价清单!K123 -> 0.3227991
A25: Wan3.0 1080p | B25: =建议售价清单!G124 -> 12 | C25: =建议售价清单!K124 -> 0.27492447
A26: Wan3.0 1080p | B26: =建议售价清单!G125 -> 18 | C26: =建议售价清单!K125 -> 0.24686192
A27: Wan3.0 1080p | B27: =建议售价清单!G126 -> 24 | C27: =建议售价清单!K126 -> 0.22680412
A28: Wan3.0 1080p | B28: =建议售价清单!G127 -> 36 | C28: =建议售价清单!K127 -> 0.19893191
A29: Wan3.0 1080p 编辑延长 | B29: =建议售价清单!G163 -> 12 | C29: =建议售价清单!K163 -> 0.27492447
A30: Wan3.0 1080p 编辑延长 | B30: =建议售价清单!G165 -> 18 | C30: =建议售价清单!K165 -> 0.24686192
A31: Wan3.0 1080p 编辑延长 | B31: =建议售价清单!G167 -> 24 | C31: =建议售价清单!K167 -> 0.22680412
A32: Wan3.0 1080p 编辑延长 | B32: =建议售价清单!G169 -> 30 | C32: =建议售价清单!K169 -> 0.21156373
A33: Wan3.0 1080p 编辑延长 | B33: =建议售价清单!G171 -> 42 | C33: =建议售价清单!K171 -> 0.18824894
A34: H3 768p | B34: =建议售价清单!G67 -> 2 | C34: =建议售价清单!K67 -> 0.3993994
A35: H3 768p | B35: =建议售价清单!G68 -> 2.5 | C35: =建议售价清单!K68 -> 0.38423645
A36: H3 768p | B36: =建议售价清单!G69 -> 3 | C36: =建议售价清单!K69 -> 0.37106918
A37: H3 768p | B37: =建议售价清单!G70 -> 3.5 | C37: =建议售价清单!K70 -> 0.36014625
A38: H3 768p | B38: =建议售价清单!G71 -> 4 | C38: =建议售价清单!K71 -> 0.35170178
A39: H3 768p | B39: =建议售价清单!G72 -> 4.5 | C39: =建议售价清单!K72 -> 0.34306569
A40: H3 768p | B40: =建议售价清单!G73 -> 5 | C40: =建议售价清单!K73 -> 0.33598938
A41: H3 768p | B41: =建议售价清单!G74 -> 5.5 | C41: =建议售价清单!K74 -> 0.32926829
A42: H3 768p | B42: =建议售价清单!G75 -> 6 | C42: =建议售价清单!K75 -> 0.3227991
A43: H3 768p | B43: =建议售价清单!G76 -> 6.5 | C43: =建议售价清单!K76 -> 0.31722689
A44: H3 768p | B44: =建议售价清单!G77 -> 7 | C44: =建议售价清单!K77 -> 0.31237721
A45: H3 768p | B45: =建议售价清单!G78 -> 7.5 | C45: =建议售价清单!K78 -> 0.30747922
... A57: H3 2k | B57: =建议售价清单!G90 -> 12 | C57: =建议售价清单!K90 -> 0.27492447
A58: Mini 1080p | B58: =建议售价清单!G55 -> 5.832 | C58: =建议售价清单!K55 -> 0.325
A59: Mini 1080p | B59: =建议售价清单!G56 -> 7.29 | C59: =建议售价清单!K56 -> 0.30965909
A60: Mini 1080p | B60: =建议售价清单!G57 -> 8.748 | C60: =建议售价清单!K57 -> 0.29678457
A61: Mini 1080p | B61: =建议售价清单!G58 -> 10.206 | C61: =建议售价清单!K58 -> 0.28629371
A62: Mini 1080p | B62: =建议售价清单!G59 -> 11.664 | C62: =建议售价清单!K59 -> 0.27687539
A63: Mini 1080p | B63: =建议售价清单!G60 -> 13.122 | C63: =建议售价清单!K60 -> 0.26856187
A64: Mini 1080p | B64: =建议售价清单!G61 -> 14.58 | C64: =建议售价清单!K61 -> 0.26139818
A65: Mini 1080p | B65: =建议售价清单!G62 -> 16.038 | C65: =建议售价清单!K62 -> 0.25473978
A66: Mini 1080p | B66: =建议售价清单!G63 -> 17.496 | C66: =建议售价清单!K63 -> 0.2487763
A67: Mini 1080p | B67: =建议售价清单!G64 -> 18.954 | C67: =建议售价清单!K64 -> 0.24335329
A68: Mini 1080p | B68: =建议售价清单!G65 -> 20.412 | C68: =建议售价清单!K65 -> 0.23807391
A69: Mini 1080p | B69: =建议售价清单!G66 -> 21.87 | C69: =建议售价清单!K66 -> 0.23343849
A70: 2.5 1080p(Ark) | B70: =建议售价清单!G8 -> 36.45 | C70: =建议售价清单!K8 -> 0.1980198
A71: 2.5 1080p(Ark) | B71: =建议售价清单!G9 -> 72.9 | C71: =建议售价清单!K9 -> 0.15005247
